{"id":2827925872,"url":"http://farm4.staticflickr.com/3265/2827925872_19c5293c4b.jpg","path":"357/737/3577375459ec74516b39f71b7d509bff.jpg","date":"2008-02-27","year":2008,"month":2,"lon":168.82416,"lat":-44.9354,"tags":"arrowtown,hdr,new+zealand,queenstown,south+island","S2CellId":"5140000000000000","result":5964,"accuracy":0.02856963,"title":"HDR+-+Arrowtown+New+Zealand+4"}
{"id":7287191956,"url":"http://farm8.staticflickr.com/7095/7287191956_6ec176e81d.jpg","path":"45c/141/45c141525cb62ff4b67dcc2596321312.jpg","date":"2012-02-11","year":2012,"month":2,"lon":168.22752,"lat":-44.540817,"tags":"day+3,mt+aspiring+national+park,new+zealand,olivine+ledge,tramping","S2CellId":"a9d5c00000000000","result":9945,"accuracy":0.30751044,"title":"Fiery+Creek","description":"Looking+down+from+near+Fiery+Col.%0AThe+Olivine+River+is+at+the+very+bottom.+The+lower+part+of+Bryneira+Range+is+to+its+left.+Angle+Peak+and+or+McClimont+Peak+are+one+or+two+of+the+snowy+peaks.+The+Olivine+Ledge+is+now+about+400m+below+us.%0AHelen+took+this+one.+That%27s+me+struggling+up+the+scree.%0A%0A%3Ca+href%3D%22http%3A%2F%2Floc.alize.us%2F%23%2Fflickr%3A7287191956%22+rel%3D%22nofollow%22%3ESee+where+this+picture+was+taken.%3C%2Fa%3E+%3Ca+href%3D%22http%3A%2F%2Fwww.flickr.com%2Fgroups%2Fgeotagging%2Fdiscuss%2F72157594165549916%2F%22%3E%5B%3F%5D%3C%2Fa%3E"}
{"id":4573395288,"url":"http://farm4.staticflickr.com/3310/4573395288_64f33f5572.jpg","path":"3df/2c0/3df2c02bc7cea37ffa921deb5eaf066.jpg","date":"2010-04-07","year":2010,"month":4,"lon":168.93625,"lat":-44.98896,"tags":"fauna,flora,new,plants,vacation,zealand","S2CellId":"46f9000000000000","result":3115,"accuracy":0.03693598,"title":"Detail+seepage+area+Crown+Range+Road"}
{"id":4684570190,"url":"http://farm5.staticflickr.com/4042/4684570190_d822317882.jpg","path":"be5/b90/be5b90dbdfc6ead146a9fc89d39ea27f.jpg","date":"2010-01-31","year":2010,"month":1,"lon":168.23419,"lat":-44.71777,"tags":"juntos+worldwide,rodney-mendez","S2CellId":"a9d5400000000000","result":9944,"accuracy":0.11681332,"title":"Queenstown%2C+New+Zealand","description":"%3Ca+href%3D%22http%3A%2F%2Fwww.JuntosWorldwide.com%22+rel%3D%22nofollow%22%3Ewww.JuntosWorldwide.com%3C%2Fa%3E%0A%0A%3Ca+href%3D%22http%3A%2F%2Fwww.Twitter.com%22+rel%3D%22nofollow%22%3Ewww.Twitter.com%3C%2Fa%3E%0A%0A%3Ca+href%3D%22http%3A%2F%2Fwww.Facebook.com%2FJuntosWorldwide%22+rel%3D%22nofollow%22%3Ewww.Facebook.com%2FJuntosWorldwide%3C%2Fa%3E"}
{"id":8630470153,"url":"http://farm9.staticflickr.com/8384/8630470153_08f3644aa7.jpg","path":"696/9e5/6969e596e1f57fbbfb8155f8f7f03047.jpg","date":"2013-04-01","year":2013,"month":4,"lon":168.66559,"lat":-44.482147,"tags":"%E0%B8%99%E0%B8%B4%E0%B8%A7%E0%B8%8B%E0%B8%B5%E0%B9%81%E0%B8%A5%E0%B8%99%E0%B8%94%E0%B9%8C,%E3%83%8B%E3%83%A5%E3%83%BC%E3%82%B8%E3%83%BC%E3%83%A9%E3%83%B3%E3%83%89,%E6%96%B0%E8%A5%BF%E5%85%B0,2013,autumn,cows,fall,mount+aspiring+national+park,new+zealand,nouvelle-z%C3%A9lande,rob+roy+track,south+island,sunny","S2CellId":"a9d5c00000000000","result":9945,"accuracy":0.11488241,"title":"Mount+Aspiring+National+Park"}
{"id":2140142739,"url":"http://farm3.staticflickr.com/2187/2140142739_0d92e3492a.jpg","path":"e5d/d35/e5dd3576fcca5f1f42c192cb75e5f9a.jpg","date":"2007-11-25","year":2007,"month":11,"lon":168.34886,"lat":-44.719025,"tags":"location,lord+of+the+rings,new+zealand+2007,queenstown","S2CellId":"88d0a631cabb5071","result":8563,"accuracy":0.011023611,"title":"Ride+of+the+Rings","description":"Photo+by+Pa"}
{"id":8374482625,"url":"http://farm9.staticflickr.com/8226/8374482625_8376872df0.jpg","path":"37e/723/37e7233a6439a6a48f75a2f68e5ff.jpg","date":"2012-11-30","year":2012,"month":11,"lon":168.34465,"lat":-44.639465,"tags":"dan%27s+paddock,filming+location,forest,glenorchy,isengard,new+zealand,otago,paddock,paradise,the+fellowship+of+the+ring,the+lord+of+the+rings","S2CellId":"5404000000000000","result":6091,"accuracy":0.47500214,"title":"Dan%27s+Paddock","description":"Seen+in+The+Fellowship+of+the+Ring+as+the+edge+of+Isengard.%0A%3Ca+href%3D%22http%3A%2F%2Fmoviemaps.org%2Flocations%2F1zb%22+rel%3D%22nofollow%22%3Emoviemaps.org%2Flocations%2F1zb%3C%2Fa%3E"}
{"id":376405187,"url":"http://farm1.staticflickr.com/146/376405187_65cfaa46b1.jpg","path":"11d/93e/11d93e4a4abc231498dfca8d917fa8a.jpg","date":"2007-01-13","year":2007,"month":1,"lon":168.86467,"lat":-44.97381,"tags":"20070113,nz,trip","S2CellId":"a9d5400000000000","result":9944,"accuracy":0.1668053,"title":"DSC04902","description":"See+where+this+photo+was+taken+at+%3Ca+href%3D%22http%3A%2F%2Fmaps.yuan.cc%2F%22+rel%3D%22nofollow%22%3Emaps.yuan.cc%2F%3C%2Fa%3E."}
{"id":1465377978,"url":"http://farm2.staticflickr.com/1332/1465377978_cc7cb29cf6.jpg","path":"bcf/86b/bcf86bdc8dae92434b4809f60b16f1.jpg","date":"2007-09-28","year":2007,"month":9,"lon":168.09752,"lat":-44.876797,"tags":"landscape,milfordroad,newzealand","S2CellId":"aa7c000000000000","result":9951,"accuracy":0.15868948,"title":"Lake+Gunn"}
{"id":3466346819,"url":"http://farm4.staticflickr.com/3573/3466346819_7ab425f89e.jpg","path":"6f7/cbb/6f7cbbd66ed11a50eb49e7b4703658.jpg","date":"2009-04-12","year":2009,"month":4,"lon":168.12727,"lat":-44.815723,"tags":"blog,bonsai,hiking,key+summit,mist,new+zealand,routeburn,south+island,tour20090408-20090418,tour20090408-20090418-4,track,tramping,tree","S2CellId":"1dcc67c000000000","result":1454,"accuracy":0.03823161,"title":"Bonsai"}
{"id":4556572939,"url":"http://farm4.staticflickr.com/3019/4556572939_5d1f448596.jpg","path":"eb6/0f6/eb60f6d0171be85ceeebbb407165ba8d.jpg","date":"2010-04-16","year":2010,"month":4,"lon":168.97342,"lat":-44.647224,"tags":"diamond,lake,new+zealand,reflections,rosa,tokina+at-x+124,trees,walk,wanaka","S2CellId":"a9d5400000000000","result":9944,"accuracy":0.4043733,"title":"perfect+reflections","description":"Diamond+Lake%2C+Wanaka%2C+New+Zealand+%5B2010%5D"}
{"id":2401438201,"url":"http://farm4.staticflickr.com/3253/2401438201_100d56a907.jpg","path":"28a/a63/28aa63a073d4398fb868e021f7de754a.jpg","date":"2008-03-04","year":2008,"month":3,"lon":168.11005,"lat":-44.631527,"tags":"new+zealand,routeburn+track,tramping,travel","S2CellId":"bdf0000000000000","result":9967,"accuracy":0.07752921,"title":"New+Zealand%3A+The+Routeburn+Track","description":"Morgen+and+I+did+a+3-day%2C+2-night+tramp+on+the+Routeburn+Track.++Saw+amazing+scenery%2C+lived+off+ramen+noodles+%26+non-refrigerated+processed+cheese+%28and+pepper+packets%29%2C+and+had+an+altogether+rewarding+time.%0A%0ADay+1."}
{"id":2566880089,"url":"http://farm4.staticflickr.com/3003/2566880089_59a66038af.jpg","path":"d07/bc4/d07bc413ccc75078a3fea5faa377143.jpg","date":"2008-05-16","year":2008,"month":5,"lon":168.84047,"lat":-44.94451,"tags":"2008,arrowtown,new+zealand,phonebox","S2CellId":"487e790000000000","result":5652,"accuracy":0.012803431,"title":"NZ_Day_4_45"}
{"id":2666394359,"url":"http://farm4.staticflickr.com/3080/2666394359_de45fe098c.jpg","path":"e6a/d8f/e6ad8f428f3ce1a6d7357ca7e1897f9.jpg","date":"2008-07-13","year":2008,"month":7,"lon":168.86913,"lat":-44.637268,"tags":"dude,lakewanaka,nz,powder,queenstown,ride,treblecone,wanaka,winterfest","S2CellId":"4789700000000000","result":3638,"accuracy":0.03199787,"title":"Mon+pote+de+ride+du+New+Mexique"}
{"id":376565083,"url":"http://farm1.staticflickr.com/146/376565083_8f7a3e799b.jpg","path":"5df/95f/5df95f841c43c5854b636260a563ae25.jpg","date":"2007-01-14","year":2007,"month":1,"lon":168.07257,"lat":-44.89503,"tags":"20070114,hh,nz,trip","S2CellId":"961c000000000000","result":9868,"accuracy":0.24401426,"title":"IMG_3587","description":"See+where+this+photo+was+taken+at+%3Ca+href%3D%22http%3A%2F%2Fmaps.yuan.cc%2F%22+rel%3D%22nofollow%22%3Emaps.yuan.cc%2F%3C%2Fa%3E."}
{"id":8032410665,"url":"http://farm9.staticflickr.com/8311/8032410665_4d44ac3c0c.jpg","path":"d32/e7c/d32e7cdc1f537dd1bf7f1a18abd7bc.jpg","date":"2012-02-14","year":2012,"month":2,"lon":168.81007,"lat":-44.98878,"tags":"2012,clouds,hayes,lake,landscape,mangrove,mountains,new+zealand,otago,shore,south+island,vista","S2CellId":"3770000000000000","result":2436,"accuracy":0.36572498,"title":"Lake+Hayes+and+mangrove","description":"I+could+be+wrong+about+which+lake+this+is%2C+but+I+think+it+is+Lake+Hayes"}
{"id":376425765,"url":"http://farm1.staticflickr.com/166/376425765_73a9e7b0c2.jpg","path":"ecb/bcb/ecbbcbc14492b8bc6d6936a481cc10.jpg","date":"2007-01-13","year":2007,"month":1,"lon":168.93945,"lat":-44.99479,"tags":"20070113,nz,trip","S2CellId":"a9d5400000000000","result":9944,"accuracy":0.41456786,"title":"IMG_3379","description":"See+where+this+photo+was+taken+at+%3Ca+href%3D%22http%3A%2F%2Fmaps.yuan.cc%2F%22+rel%3D%22nofollow%22%3Emaps.yuan.cc%2F%3C%2Fa%3E."}
{"id":5993453224,"url":"http://farm7.staticflickr.com/6129/5993453224_bd100184b1.jpg","path":"995/d80/995d8057251a6f345aa828127f1ddbd.jpg","date":"2009-01-17","year":2009,"month":1,"lon":168.39578,"lat":-44.78518,"tags":"%5Eloc,australasia,flickr-all,glenorchy,new+zealand,otago","S2CellId":"a9d5c00000000000","result":9945,"accuracy":0.20334087,"title":"20090117-130804","description":"Neil+Stead"}
{"id":2388088890,"url":"http://farm3.staticflickr.com/2108/2388088890_52a1ffa25c.jpg","path":"d08/551/d08551feafff759e7d0a2875d34bf67.jpg","date":"2008-03-26","year":2008,"month":3,"lon":168.00842,"lat":-44.959816,"tags":"newzealand","S2CellId":"a9d4400000000000","result":9942,"accuracy":0.24783699,"title":"Protect+Our+Waters"}
{"id":3208210992,"url":"http://farm4.staticflickr.com/3387/3208210992_c61f12743f.jpg","path":"dfd/1b0/dfd1b0885f4738df486ad7d96ec834ef.jpg","date":"2009-01-12","year":2009,"month":1,"lon":168.23914,"lat":-44.71608,"tags":"blog57,new+zealand,routeburn,routeburn+day+3","S2CellId":"1367000000000000","result":1190,"accuracy":0.019725818,"title":"Aaron+Freezing+in+the+stream"}
{"id":8148938176,"url":"http://farm9.staticflickr.com/8193/8148938176_46b3b194af.jpg","path":"489/6b5/4896b5c6d1efcb5ad0dc848f85e93398.jpg","date":"2012-02-16","year":2012,"month":2,"lon":168.98853,"lat":-44.65467,"tags":"2012,blue+sky,filter,lake,new+zealand,otago,otago-nz,polarizing,south+island,wanaka","S2CellId":"a9d5400000000000","result":9944,"accuracy":0.25186682,"title":"Lake+Wanaka"}
{"id":5993213816,"url":"http://farm7.staticflickr.com/6140/5993213816_12810cf87e.jpg","path":"23f/888/23f8887897efd7734e74099af3e19df.jpg","date":"2009-01-12","year":2009,"month":1,"lon":168.0999,"lat":-44.804806,"tags":"%5Eloc,australasia,fiordland,flickr-all,glenorchy,new+zealand,otago","S2CellId":"36f4000000000000","result":2416,"accuracy":0.09608895,"title":"20090112-124659","description":"Neil+Stead"}
{"id":2743058530,"url":"http://farm4.staticflickr.com/3271/2743058530_53b8c5456b.jpg","path":"c7b/bcf/c7bbcf224b39196f26693a38375e7fa.jpg","date":"2008-07-19","year":2008,"month":7,"lon":168.09906,"lat":-44.72332,"tags":"fiordlands","S2CellId":"a9d5c00000000000","result":9945,"accuracy":0.5633663,"title":"IMG_4068"}
{"id":3061110542,"url":"http://farm4.staticflickr.com/3286/3061110542_01e5ffbc4f.jpg","path":"eb1/463/eb14639e75d7eacf2d617ce9f426958.jpg","date":"2008-11-23","year":2008,"month":11,"lon":168.72237,"lat":-44.480953,"tags":"rivi%C3%A8re,robroytrack","S2CellId":"548ec00000000000","result":6159,"accuracy":0.040758383,"title":"Bord+dla+Rivi%C3%A9re"}
{"id":5993478832,"url":"http://farm7.staticflickr.com/6010/5993478832_e98e8e689d.jpg","path":"ddf/686/ddf686e54d28d127e8c97c0a4c9d.jpg","date":"2009-01-17","year":2009,"month":1,"lon":168.34717,"lat":-44.705513,"tags":"%5Eloc,australasia,flickr-all,glenorchy,new+zealand,otago","S2CellId":"488c400000000000","result":5764,"accuracy":0.13223335,"title":"20090117-152436","description":"Neil+Stead"}
{"id":7307969326,"url":"http://farm8.staticflickr.com/7237/7307969326_26ddfe2bae.jpg","path":"f35/0d5/f350d54facc41da8a1a99913a2e0b416.jpg","date":"2012-02-13","year":2012,"month":2,"lon":168.19836,"lat":-44.634144,"tags":"darran+mountains,day+5,mt+aspiring+national+park,new+zealand,tramping,west+coast","S2CellId":"a9d5c00000000000","result":9945,"accuracy":0.5975122,"title":"Mt+Madeline+and+Mt+Tutuko","description":"To+get+to+North+Col+from+Lake+Nerine%2C+you+climb+about+100m+over+the+western+ridge+of+the+lake+and+then+traverse+south-southwest+through+some+wonderful+boulders+and+snow+grass+%28admittedly+much+like+the+terrors+of+the+previous+day%2C+but+this+time+when+you%27re+fresh%2C+rather+than+at+the+end+of+the+day%29.+The+view+west+%28towards+Milford+Sound%21%29+is+fabulous.%0A%0A%3Ca+href%3D%22http%3A%2F%2Floc.alize.us%2F%23%2Fflickr%3A7307969326%22+rel%3D%22nofollow%22%3ESee+where+this+picture+was+taken.%3C%2Fa%3E+%3Ca+href%3D%22http%3A%2F%2Fwww.flickr.com%2Fgroups%2Fgeotagging%2Fdiscuss%2F72157594165549916%2F%22%3E%5B%3F%5D%3C%2Fa%3E"}
{"id":283476893,"url":"http://farm1.staticflickr.com/120/283476893_0e02839854.jpg","path":"4bb/75f/4bb75f2f04b3b3a37c919525ba37d8b.jpg","date":"2005-11-12","year":2005,"month":11,"lon":168.24583,"lat":-44.73393,"tags":"hiking,new+zealand,routeburn,tramping","S2CellId":"0d56c00000000000","result":472,"accuracy":0.013155631,"title":"i111505+132"}
{"id":243031897,"url":"http://farm1.staticflickr.com/89/243031897_9962a46f27.jpg","path":"cfd/214/cfd21423734da2104b771d8eb0673bf5.jpg","date":"2006-09-05","year":2006,"month":9,"lon":168.93402,"lat":-44.617477,"tags":"new+zealand,road,treble+cone,tree,tree+and+road,winter,winter+colours","S2CellId":"a9d5c00000000000","result":9945,"accuracy":0.110834494,"title":"A+road+and+a+tree"}
{"id":8360901662,"url":"http://farm9.staticflickr.com/8507/8360901662_a83e2f95a9.jpg","path":"883/333/883333262539f055dec9e556e8b6b099.jpg","date":"2013-01-07","year":2013,"month":1,"lon":168.1763,"lat":-44.763187,"tags":"newzealand,zealand","S2CellId":"548e400000000000","result":6158,"accuracy":0.12355517}
{"id":4434264799,"url":"http://farm5.staticflickr.com/4013/4434264799_3c6fbccedd.jpg","path":"b8b/80c/b8b80cadd6e1796e3db167cf65c9622.jpg","date":"2010-02-07","year":2010,"month":2,"lon":168.07869,"lat":-44.81761,"tags":"neuseeland+2010,tokina+at-x+116+pro+dx+af+11-16mm+f%2F2.8","S2CellId":"6d6b000000000000","result":6849,"accuracy":0.05402272,"title":"Milford+Road+State+Highway+94"}
{"id":376490836,"url":"http://farm1.staticflickr.com/145/376490836_67b22a096a.jpg","path":"fa4/20d/fa420d497cc8b8e52381bbf4230ce.jpg","date":"2007-01-14","year":2007,"month":1,"lon":168.10536,"lat":-44.80913,"tags":"20070114,nz,trip","S2CellId":"6b12700000000000","result":6668,"accuracy":0.17852405,"title":"DSC05192","description":"See+where+this+photo+was+taken+at+%3Ca+href%3D%22http%3A%2F%2Fmaps.yuan.cc%2F%22+rel%3D%22nofollow%22%3Emaps.yuan.cc%2F%3C%2Fa%3E."}
{"id":8383253476,"url":"http://farm9.staticflickr.com/8091/8383253476_a2e50a541e.jpg","path":"b4c/b40/b4cb40307829dcad3239bfb676d54aa.jpg","date":"2012-11-30","year":2012,"month":11,"lon":168.67206,"lat":-44.98825,"tags":"arthurs+point,boat,jetboat,new+zealand,otago,shotover+jet,shotover+river","S2CellId":"539c000000000000","result":6069,"accuracy":0.28350815,"title":"Down+the+Gorge"}
{"id":4594169379,"url":"http://farm2.staticflickr.com/1043/4594169379_f6f8ddf1b7.jpg","path":"825/a4f/825a4f1b86fecdbbfefca78b8fccbf8.jpg","date":"2010-04-29","year":2010,"month":4,"lon":168.81682,"lat":-44.97225,"tags":"hayes,lake,new+zealand,nz,photocontest-tnc10,queenstown","S2CellId":"8864650000000000","result":8461,"accuracy":0.03865244,"title":"Lake+Hayes","description":"When+I+arrived+in+Queenstown+I+did+some+scouting+and+Lake+Hayes+was+the+first+place+I+visited.+There+was+light+rain+around+and+it+was+pretty+gloomy%2C+so+the+lake+looked+pretty+uninspiring+to+say+the+least.+%0A%0AThe+forecast+was+for+more+wind+and+rain+for+the+rest+of+the+week+so+I+wasn%27t+too+hopeful+about+getting+any+shots+from+here.+%0A%0ABut%2C+a+couple+of+days+into+the+trip+I+happened+to+drive+by+the+lake+early+in+the+morning+when+there+were+blue+skies+and+very+little+wind%21+Needless+to+say+I+stopped+the+car+and+took+some+shots+in+a+hurry.+%0A%0AA+few+minutes+later+the+wind+started+up+again+and+the+clouds+blanketed+the+sky+-+back+to+gloominess+but+at+least+I+got+a+shot.%0A%0A%3Ca+href%3D%22http%3A%2F%2Fbighugelabs.com%2Fonblack.php%3Fid%3D4594169379%26size%3Dlarge%22+rel%3D%22nofollow%22%3EView+Large+On+Black%3C%2Fa%3E"}
{"id":4688230372,"url":"http://farm5.staticflickr.com/4037/4688230372_60ee31178c.jpg","path":"7dd/9d1/7dd9d1f8c2a17541fcec70ab2da29c.jpg","date":"2010-05-23","year":2010,"month":5,"lon":168.021,"lat":-44.800507,"tags":"fiordland+national+park,monkey+creek","S2CellId":"a9d5c00000000000","result":9945,"accuracy":0.8215842,"title":"Monkey+Creek+in+Fiordland+National+Park","description":"Monkey+Creek+in+Fiordland+National+Park"}
{"id":13376450703,"url":"http://farm8.staticflickr.com/7013/13376450703_5f873da606.jpg","path":"605/135/605135cfb56964317b1b8edb71e39a.jpg","date":"2014-03-22","year":2014,"month":3,"lon":168.38914,"lat":-44.845955,"tags":"glenorchy,glenorchy-walkway,lake-wakatipu,new-zealand,south-island","S2CellId":"4807400000000000","result":4766,"accuracy":0.02267313,"title":"DSC07728"}
{"id":5992910241,"url":"http://farm7.staticflickr.com/6138/5992910241_3c7517396f.jpg","path":"66a/23b/66a23b905933e16639f0bd777799ff48.jpg","date":"2009-01-17","year":2009,"month":1,"lon":168.31273,"lat":-44.657547,"tags":"%5Eloc,australasia,flickr-all,glenorchy,new+zealand,otago","S2CellId":"5470000000000000","result":6094,"accuracy":0.108730346,"title":"20090117-142148","description":"Neil+Stead"}
{"id":12258518734,"url":"http://farm4.staticflickr.com/3719/12258518734_6f88a8a0f8.jpg","path":"dfd/b4c/dfdb4c5260a21ad9ad1fbe88932e9bd2.jpg","date":"2013-03-18","year":2013,"month":3,"lon":168.96498,"lat":-44.646378,"tags":"diamond+lake,lake,neuseeland,new+zealand,otago,wanaka","S2CellId":"4889300000000000","result":5756,"accuracy":0.12390438,"title":"Above+Diamond+Lake"}
{"id":10983959594,"url":"http://farm8.staticflickr.com/7301/10983959594_a619111fab.jpg","path":"969/821/969821cbbb529a44ed19114eaf95f6bd.jpg","date":"2013-10-28","year":2013,"month":10,"lon":168.39984,"lat":-44.874172,"tags":"%2Bgenre,%2Bnature,%2Btechnique,%2Bthing,%2Btreatment,geo,glenorchy,hdr,lake,lake+wakitipu,landscape,monochrome,mountain,new+zealand,otago,queenstown,remarkables,road","S2CellId":"6d2f000000000000","result":6810,"accuracy":0.3767721,"title":"Road+from+Glenorchy+-+New+Zealand+BW.jpg"}
{"id":2114627381,"url":"http://farm3.staticflickr.com/2298/2114627381_a53faf003b.jpg","path":"32d/1a8/32d1a8fcd7d7a7ce24b984874585f66e.jpg","date":"2007-11-29","year":2007,"month":11,"lon":168.31483,"lat":-44.656628,"tags":"cow,grass,new+zealand,skull","S2CellId":"485ec00000000000","result":4836,"accuracy":0.12284475,"title":"Cow+skull"}
{"id":11342666904,"url":"http://farm4.staticflickr.com/3804/11342666904_c74d9ede85.jpg","path":"2cd/1d5/2cd1d5803d7020198f3b4666533eace9.jpg","date":"2013-10-30","year":2013,"month":10,"lon":168.56787,"lat":-44.997158,"tags":"mike+lake,new+zealand,south+island","S2CellId":"a9d5400000000000","result":9944,"accuracy":0.5389006,"title":"Moke+Lake+Hike%2C+Queenstown","description":"This+was+probably+one+of+my+most+favorite+parts+of+our+NZ+trip."}
{"id":4546986723,"url":"http://farm5.staticflickr.com/4021/4546986723_146ff2ee11.jpg","path":"2f5/d76/2f5d7659b73b8531fe61e8e2aafa5658.jpg","date":"2010-04-15","year":2010,"month":4,"lon":168.81007,"lat":-44.48083,"tags":"aspiring,cows,mount,mountains,national,new+zealand,park,river,tokina+at-x+124","S2CellId":"42c0000000000000","result":2742,"accuracy":0.20861584,"description":"Mount+Aspiring+National+Park%2C+New+Zealand+%5B2010%5D"}
{"id":13399098175,"url":"http://farm8.staticflickr.com/7271/13399098175_f84c5ea385.jpg","path":"5db/ffd/5dbffda05c2d6b51a787de4d5762910.jpg","date":"2014-03-25","year":2014,"month":3,"lon":168.56488,"lat":-44.997387,"tags":"new-zealand,queenstown,south-island","S2CellId":"a9d5400000000000","result":9944,"accuracy":0.24235585,"title":"DSC08432"}
{"id":4202731792,"url":"http://farm3.staticflickr.com/2512/4202731792_7de55172aa.jpg","path":"92c/a82/92ca821ad3954ad1a5417826e00efb8.jpg","date":"2009-11-20","year":2009,"month":11,"lon":168.96999,"lat":-44.931732,"tags":"mountain,new+zealand,scenery,view","S2CellId":"91d5c00000000000","result":9634,"accuracy":0.13368414,"title":"newzealand_2009_492"}
{"id":283521733,"url":"http://farm1.staticflickr.com/99/283521733_349f772fbd.jpg","path":"e73/830/e73830528d80ba1c245535d132a520f0.jpg","date":"2005-11-13","year":2005,"month":11,"lon":168.24583,"lat":-44.73393,"tags":"conical+hill,hiking,new+zealand,routeburn,tramping","S2CellId":"4ec0000000000000","result":5959,"accuracy":0.016901359,"title":"NZ+Alpine%2C+Conical+Hill","description":"i111505+256"}
{"id":7478175776,"url":"http://farm9.staticflickr.com/8161/7478175776_613e8b2bbf.jpg","path":"47b/f8e/47bf8e8e89ba168886f394b2bd9691.jpg","date":"2012-02-16","year":2012,"month":2,"lon":168.80464,"lat":-44.48176,"tags":"matukituki+river+east+branch,my+aspiring+national+park,new+zealand,tramping","S2CellId":"548e400000000000","result":6158,"accuracy":0.21938454,"title":"East+meets+West+%28Matukituki%29","description":"Very+first+thing+to+do+in+this+tramp+is+get+your+feet+wet+crossing+the+West+Matukituki.%0A%0A%3Ca+href%3D%22http%3A%2F%2Floc.alize.us%2F%23%2Fflickr%3A7478175776%22+rel%3D%22nofollow%22%3ESee+where+this+picture+was+taken.%3C%2Fa%3E+%3Ca+href%3D%22http%3A%2F%2Fwww.flickr.com%2Fgroups%2Fgeotagging%2Fdiscuss%2F72157594165549916%2F%22%3E%5B%3F%5D%3C%2Fa%3E"}
{"id":204712933,"url":"http://farm1.staticflickr.com/61/204712933_14a7870b39.jpg","path":"413/4a5/4134a56a36590b4767ff2d8fa17792.jpg","date":"2006-01-31","year":2006,"month":1,"lon":168.88527,"lat":-44.26192,"tags":"bushwalking,canon+powershot+a520,mt+aspiring,new+zealand,nz,south+island,wilkin+river","S2CellId":"a9d5c00000000000","result":9945,"accuracy":0.07940834,"title":"Lakes+above+Top+Forks","description":"Mt+Aspiring+National+Park%2C+South+Island%2C+New+Zealand"}
{"id":5980512780,"url":"http://farm7.staticflickr.com/6142/5980512780_74007ba2d1.jpg","path":"2dc/3e5/2dc3e5fa19c5f425fcd692bb712e3a54.jpg","date":"2011-01-06","year":2011,"month":1,"lon":168.38152,"lat":-44.73233,"tags":"country,glenorchy,new+zealand,queenstown,south+island","S2CellId":"4889300000000000","result":5756,"accuracy":0.03608593,"title":"New+Zealand+Trip_065_060111"}
{"id":5487613339,"url":"http://farm6.staticflickr.com/5173/5487613339_96a4282221.jpg","path":"f29/968/f29968fed75f8442a3349db957b3131.jpg","date":"2011-01-04","year":2011,"month":1,"lon":168.11897,"lat":-44.675,"tags":"country,fjordland,hollyford+river,milford+sound,new+zealand,south+island","S2CellId":"bc50000000000000","result":9959,"accuracy":0.16547452,"title":"Hollyford+River_17_040111"}
{"id":7393401156,"url":"http://farm6.staticflickr.com/5236/7393401156_092caa7773.jpg","path":"275/726/2757264b5ee07b3e66c890f3c9f7bd9c.jpg","date":"2011-02-21","year":2011,"month":2,"lon":168.39967,"lat":-44.877167,"tags":"50mm+f%2F1.8+e,gf1,glenorchy,mountains,new+zealand,road,south+island,southern+alps","S2CellId":"56cd000000000000","result":6324,"accuracy":0.2667289,"title":"Near+Glenorchy"}
{"id":2387255223,"url":"http://farm3.staticflickr.com/2122/2387255223_8ed8937c37.jpg","path":"fb7/ec7/fb7ec73d37e962c72611e4e45d6a151f.jpg","date":"2008-03-26","year":2008,"month":3,"lon":168.07709,"lat":-44.88774,"tags":"newzealand","S2CellId":"a9d5c00000000000","result":9945,"accuracy":0.33180553,"title":"Lake+Gunn"}
{"id":283504422,"url":"http://farm1.staticflickr.com/122/283504422_cf4e27d76c.jpg","path":"757/de4/757de426fe772ae84951dd80bd859179.jpg","date":"2005-11-13","year":2005,"month":11,"lon":168.24583,"lat":-44.73393,"tags":"hiking,new+zealand,routeburn,tramping","S2CellId":"a9d5c00000000000","result":9945,"accuracy":0.13704023,"title":"i111505+224"}
{"id":5993219680,"url":"http://farm7.staticflickr.com/6023/5993219680_cdb6c2f51e.jpg","path":"332/472/332472668e5acfbfe248403d15329b.jpg","date":"2009-01-12","year":2009,"month":1,"lon":168.0999,"lat":-44.804806,"tags":"%5Eloc,australasia,fiordland,flickr-all,glenorchy,new+zealand,otago","S2CellId":"6d6b000000000000","result":6849,"accuracy":0.1527691,"title":"20090112-125251","description":"Neil+Stead"}
{"id":13372033413,"url":"http://farm4.staticflickr.com/3699/13372033413_fd1d0d9dbe.jpg","path":"201/71d/20171daf1ba3c4014dfdb331322f8d.jpg","date":"2014-03-23","year":2014,"month":3,"lon":168.26866,"lat":-44.71314,"tags":"glenorchy,new-zealand,south-island","S2CellId":"54bf400000000000","result":6299,"accuracy":0.040643945,"title":"DSC07947"}
{"id":2961139046,"url":"http://farm4.staticflickr.com/3061/2961139046_f59c1e4fc8.jpg","path":"8f8/518/8f8518deabb9a3bdb1623b4554abe.jpg","date":"2008-10-18","year":2008,"month":10,"lon":168.45268,"lat":-44.851486,"tags":"bird,glenorchy,heatherjockhut,jeanhut,kea,keabird,mtalaska,mtlarkins,mtmcintosh,nz,rando,southlakes","S2CellId":"48650c0000000000","result":4871,"accuracy":0.045968633,"title":"Kea+on+the+roof+1"}
{"id":283458809,"url":"http://farm1.staticflickr.com/103/283458809_69585f522d.jpg","path":"9bc/023/9bc023a7585777ed1b83f9c5f651b2be.jpg","date":"2005-11-12","year":2005,"month":11,"lon":168.24583,"lat":-44.73393,"tags":"hiking,key+summit,new+zealand,routeburn,tramping","S2CellId":"6d2f000000000000","result":6810,"accuracy":0.037185334,"title":"i111505+075"}
{"id":8236622038,"url":"http://farm9.staticflickr.com/8204/8236622038_148e1bcd26.jpg","path":"2c4/5f2/2c45f2398c7dc3704e8b2c53c0dfdf93.jpg","date":"2012-11-28","year":2012,"month":11,"lon":168.6985,"lat":-44.487198,"tags":"ds5000,hiking,new+zealand,rob+roy+glacier,rtw,south+island,wanaka","S2CellId":"6d2b000000000000","result":6808,"accuracy":0.22081532,"title":"Whizzing+past+on+the+dirt+track+back+to+Wanaka"}
