{"id":2922970711,"url":"http://farm4.staticflickr.com/3220/2922970711_7b2ab4f1f4.jpg","path":"467/e2b/467e2bb1bc18ea452fe9b6b2c571d63.jpg","date":"2008-10-07","year":2008,"month":10,"lon":-72.652504,"lat":-38.724827,"tags":"abstracto,desenfoque,green,hoja,macro,verde","S2CellId":"3a52400000000000","result":2515,"accuracy":0.018489128,"title":"The+Winner+is","description":"Little+Miss+Sunshine+%2F%2F+Soundtrack%0A%0A%3Ci%3E%22Detras+de+las+hojas+esperamos+que+pasara+la+tormenta%22%3C%2Fi%3E"}
{"id":3142322392,"url":"http://farm4.staticflickr.com/3234/3142322392_2c5332afe7.jpg","path":"838/7ca/8387ca1ea1fe353b380f3f6475d98b2.jpg","date":"2008-12-27","year":2008,"month":12,"lon":-72.57561,"lat":-38.72932,"tags":"%5Bp.thiers%5D,100asa,a-1,canon,cerro,chile,image,nielol,philippe+thiers,photowalk,pro,temuco","S2CellId":"9669000000000000","result":9899,"accuracy":0.011394289,"title":"A+la+natalia+la+ataca+un+campo+de+fuerza"}
{"id":509401669,"url":"http://farm1.staticflickr.com/212/509401669_a6d7ef5d21.jpg","path":"ecf/0d4/ecf0d488ed27a2edabf6d514ddfbea.jpg","date":"2007-05-21","year":2007,"month":5,"lon":-72.63748,"lat":-38.9865,"tags":"2007,pitrufquen","S2CellId":"80dd317000000000","result":7376,"accuracy":0.013303077,"title":"Salmones+ahumados"}
{"id":247531143,"url":"http://farm1.staticflickr.com/93/247531143_2cd78bb91c.jpg","path":"422/ac7/422ac711e3cf04c152443d963edd435.jpg","date":"2006-09-17","year":2006,"month":9,"lon":-72.16267,"lat":-38.6705,"tags":"araucania,chile,llaima,nieve,novena+region,temuco,volcan,volcan+llaima","S2CellId":"9615000000000000","result":9866,"accuracy":0.07824933,"title":"volcan+llaima","description":"Camino+hacia+el+volcan+llaima...."}
{"id":2769624863,"url":"http://farm4.staticflickr.com/3285/2769624863_22bb80b9d3.jpg","path":"bca/6e1/bca6e12694b9b9aebbd25cd1b8695a8.jpg","date":"2008-03-23","year":2008,"month":3,"lon":-72.579285,"lat":-38.733665,"tags":"asado,bomberos,celebracion,fiesta,temuco","S2CellId":"54906ab300000000","result":6212,"accuracy":0.0047922847,"title":"Another+Party","description":"Rescue+Team"}
{"id":3419919653,"url":"http://farm4.staticflickr.com/3655/3419919653_18532b63b5.jpg","path":"bf4/4cf/bf44cf8dd33a06d33464988b3e25.jpg","date":"2008-01-01","year":2008,"month":1,"lon":-72.42719,"lat":-38.475163,"tags":"llaima,volcan","S2CellId":"9615000000000000","result":9866,"accuracy":0.14937961,"title":"Erupcion+Volcan+Llaima+Enero+2008"}
{"id":8380942411,"url":"http://farm9.staticflickr.com/8471/8380942411_3394777cf6.jpg","path":"271/978/27197842f9a2fe62fd707677c973c1dc.jpg","date":"2013-01-09","year":2013,"month":1,"lon":-72.547874,"lat":-38.702618,"tags":"araucan%C3%ADa,campus+norte+uct,fashion,fernanda,model,modelo,mujer,rrojasfx,temuco,woman","S2CellId":"8869700000000000","result":8478,"accuracy":0.051152356,"title":"Fernanda+04+-+Laguna+Campus+Norte+UCT","description":"Modelo%3A+Fernanda.%0AAsistencia%3A+Bel%C3%A9n+Jofr%C3%A9."}
{"id":6209506195,"url":"http://farm7.staticflickr.com/6231/6209506195_03ce4fdb80.jpg","path":"793/ad1/793ad11b84c75a22c784c142b461dbd9.jpg","date":"2011-10-01","year":2011,"month":10,"lon":-72.577225,"lat":-38.735405,"tags":"photowalk","S2CellId":"0d2464e400000000","result":260,"accuracy":0.051791955,"title":"Photowalk+Temuco+2011","description":"Balc%C3%B3n+del+antiguo+y+tradicional+Edificio+Marsano+%281926%29%2C+en+el+Barrio+Estaci%C3%B3n+de+Temuco"}
{"id":2815915255,"url":"http://farm4.staticflickr.com/3264/2815915255_1a93e82e4d.jpg","path":"2fa/f1d/2faf1dd9b1bd6ead417e3f1e458a73d.jpg","date":"2008-03-23","year":2008,"month":3,"lon":-72.58667,"lat":-38.737816,"tags":"araucania,bicicle,bicileta,canon,claudio+sepulveda+geoffroy,s3is,temuco,transport,transporte,wheel","S2CellId":"47c609c740000000","result":4323,"accuracy":0.019242903,"title":"4+wheel+drive","description":"alternativa+ecol%C3%B3gica+para+los+dias+lluviosos."}
{"id":6209470903,"url":"http://farm7.staticflickr.com/6216/6209470903_dd555beaf4.jpg","path":"854/4fc/8544fcb4e322cf615a4fdf58ac405ccb.jpg","date":"2011-10-01","year":2011,"month":10,"lon":-72.58667,"lat":-38.734,"tags":"photowalk","S2CellId":"9669000000000000","result":9899,"accuracy":0.02727312,"title":"Photowalk+Temuco+2011","description":"Jorge+Z%C3%BA%C3%B1iga+capturando+una+imagen+de+la+perrita+que+dormitaba+en+la+ciclov%C3%ADa+de+Avenida+Balmaceda"}
{"id":2208848024,"url":"http://farm3.staticflickr.com/2264/2208848024_92ef12bbde.jpg","path":"1fe/87b/1fe87bf08a8d98bcf032def5f7652d7b.jpg","date":"2008-01-01","year":2008,"month":1,"lon":-72.56084,"lat":-38.71391,"tags":"araucania,canon,chile,claudio+sepulveda+geoffroy,erupcion+volcan+llaima,llaima,s3is,temuco,volcan","S2CellId":"88d0a631cabb5071","result":8563,"accuracy":0.00813934,"title":"Erupci%C3%B3n+Volc%C3%A1n+Llaima","description":"Fotograf%C3%ADa+a+aproximadamente+78+Km.+al+crater%2C+desde+la+salida+norte+de+Temuco...%0AEn+esos+d%C3%ADas+improvisando+un+tripode+entre+chalecos+y+el+techo+del+auto."}
