{"id":297168343,"url":"http://farm1.staticflickr.com/119/297168343_ce25cb1918.jpg","path":"b4f/de8/b4fde8ec7b956118b749c4ddb65d7988.jpg","date":"2004-09-02","year":2004,"month":9,"lon":99.71929,"lat":27.88339,"tags":"%E4%B8%AD%E5%9B%BD,%E4%BA%91%E5%8D%97,%E7%A1%95%E9%83%BD%E6%B9%96,%E8%97%8F%E5%8C%BA,china,tibetan,yunnan","S2CellId":"4888f00000000000","result":5754,"accuracy":0.183289,"title":"%E7%A1%95%E9%83%BD%E6%B9%96+Shudu+Lake","description":"%E4%BA%91%E5%8D%97%E4%B8%AD%E7%94%B8%EF%BC%88%E9%A6%99%E6%A0%BC%E9%87%8C%E6%8B%89%EF%BC%89%0AZhongdian%28Shangri-La%29%2C+Yunnan%2C+China"}
{"id":1798802152,"url":"http://farm3.staticflickr.com/2073/1798802152_735c82aa3f.jpg","path":"419/626/419626517b4d147f1dbd2fc2bba4b273.jpg","date":"2007-10-15","year":2007,"month":10,"lon":100.0827,"lat":27.178608,"tags":"china,gorge,leaping,tiger,tiger+leaping+gorge,viajes,yunnan","S2CellId":"916d9c0000000000","result":9613,"accuracy":0.4065979,"title":"TLG%3A+vista+hacia+el+interior+del+ca%C3%B1%C3%B3n","description":"Tiger+Leaping+Gorge+%28Garganta+del+Salto+del+Tigre%29+%28%E8%99%8E%E8%B7%B3%E5%B3%A1%3B+pinyin%3A+H%C7%94ti%C3%A0o+Xi%C3%A1%29%3A+se+trata%2C+tal+vez%2C+del+ca%C3%B1%C3%B3n-garganta+m%C3%A1s+profundo+del+mundo.+Las+aguas+del+r%C3%ADo+Yangtze+se+abren+entre+verticales+paredes+de+hasta+3.900+metros+de+altitud+durante+16+kil%C3%B3metros%2C+entre+la+cordillera+de+la+monta%C3%B1a+del+Drag%C3%B3n+de+Jade+%28%E7%8E%89%E9%BE%99%E5%B1%B1%3B+Y%C3%B9l%C3%B3ng+Sh%C4%81n%29%2C+de+casi+5.600+metros+de+altitud%2C+y+la+de+la+Monta%C3%B1a+Haba+%28%E5%93%88%E5%B7%B4%E5%B1%B1%3B+H%C4%81b%C4%81+Sh%C4%81n%29%2C+de+m%C3%A1s+de+5.000+metros+tambi%C3%A9n.%0A%0ALa+leyenda+cuenta+que+un+tigre%2C+acosado+por+los+cazadores%2C+salt%C3%B3+la+garganta+de+un+extremo+al+otro+en+su+parte+m%C3%A1s+angosta.+Algo+imposible+hoy+en+d%C3%ADa%2C+pues+en+1960+un+terremoto+colaps%C3%B3+uno+de+los+pilares%2C+que+cay%C3%B3+sobre+el+r%C3%ADo+y+estuvo+a+un+tris+de+bloquear+su+curso.+La+roca+sigue+hoy+all%C3%AD+y+la+leyenda+tambi%C3%A9n.%0A%0ALa+mejor+forma+de+conocer+este+incre%C3%ADble+lugar+es+recorriendo+un+sendero+%28%22the+high+road%22%29+que+comienza+cerca+de+Qiaotou+y+acaba+en+Walnut+Grove.+Durante+aproximadamente+22+kil%C3%B3metros+se+recorre+el+ca%C3%B1%C3%B3n+a+una+altura+considerable%2C+lo+que+permite+tener+unas+vistas+muy+buenas.+El+tiempo+total+para+completarlo+es+de+unas+10-12+horas%2C+y+se+puede+dividir+en+varias+jornadas%2C+pues+hay+bastantes+sitios+para+dormir+repartidos+por+todo+el+camino."}
{"id":186827718,"url":"http://farm1.staticflickr.com/62/186827718_8479225228.jpg","path":"8da/6b0/8da6b0ba39c026e5dcc93c437193c41.jpg","date":"2004-04-01","year":2004,"month":4,"lon":99.668655,"lat":27.86154,"tags":"shangri-la,yunnan","S2CellId":"5d90000000000000","result":6336,"accuracy":0.111846365,"title":"Yunnan-191+Shangri-La","description":"Grassland+Ela+%28%E4%BE%9D%E6%8B%89%E8%8D%89%E5%8E%9F%29+without+grass+-+we+probably+went+there+in+wrong+season+%28early+Apr%29.+The+winter+here+just+ended"}
{"id":525066869,"url":"http://farm1.staticflickr.com/252/525066869_055fcb3b5e.jpg","path":"3f2/61e/3f261ef73f7fe59357c5eb85994f9551.jpg","date":"2007-05-26","year":2007,"month":5,"lon":99.70402,"lat":27.824047,"tags":"china,cnemil,diqing,shangri-la,yunnan","S2CellId":"3724000000000000","result":2419,"accuracy":0.031010954,"title":"Practicing+bike"}
{"id":8398517669,"url":"http://farm9.staticflickr.com/8475/8398517669_36e874de0a.jpg","path":"c9c/be6/c9cbe63cfb4132cd622b94aad4f2d8e4.jpg","date":"2012-10-16","year":2012,"month":10,"lon":100.66058,"lat":27.7615,"tags":"chine,lijiang,yunnan","S2CellId":"3770000000000000","result":2436,"accuracy":0.16478495,"title":"Yongning+monastery","description":"Monast%C3%A8re+de+Yongning"}
{"id":7629750372,"url":"http://farm9.staticflickr.com/8022/7629750372_e0024221ba.jpg","path":"c26/c36/c26c369f787e0b68a14c711a2f4494.jpg","date":"2012-07-03","year":2012,"month":7,"lon":99.82695,"lat":28.797327,"tags":"%E4%B9%A1%E5%9F%8E,%E5%9B%9B%E5%B7%9D,%E7%94%98%E5%AD%9C%E5%B7%9E,china,prc,sichuan,xiangcheng","S2CellId":"3724000000000000","result":2419,"accuracy":0.29477397,"title":"IMG_6829"}
{"id":5319892285,"url":"http://farm6.staticflickr.com/5050/5319892285_a4320e0a14.jpg","path":"631/76d/63176dfdbb5fba3ba279f8719f22da58.jpg","date":"2010-12-30","year":2010,"month":12,"lon":99.70441,"lat":27.861383,"tags":"china,prc,shangri-la,yunnan,zhongdian","S2CellId":"3770000000000000","result":2436,"accuracy":0.8270649,"title":"IMG_0159"}
{"id":4603758651,"url":"http://farm2.staticflickr.com/1251/4603758651_ed27c1969c.jpg","path":"d92/d57/d92d57d52923fb756df7bfe57457965.jpg","date":"2010-05-09","year":2010,"month":5,"lon":100.25556,"lat":27.102692,"tags":"china,concert,lijiang,music,show,yunnan","S2CellId":"3650000000000000","result":2395,"accuracy":0.39514193,"title":"Impression+Lijiang","description":"A+good+show+in+a+great+setting"}
{"id":4136181239,"url":"http://farm3.staticflickr.com/2796/4136181239_34af51d01c.jpg","path":"c5f/14e/c5f14e594491c59364e1eae614329.jpg","date":"2009-10-17","year":2009,"month":10,"lon":100.07214,"lat":27.19815,"tags":"china,lijiang,tiger+leaping+gorge,yangtze","S2CellId":"4045000000000000","result":2654,"accuracy":0.08833247,"title":"Corn+fileds"}
{"id":7627029568,"url":"http://farm8.staticflickr.com/7263/7627029568_75d534680a.jpg","path":"c32/e90/c32e907caab22d2fc4844779e1f3dddf.jpg","date":"2012-06-30","year":2012,"month":6,"lon":99.704956,"lat":27.814615,"tags":"%E4%B8%AD%E7%94%B8,%E4%BA%91%E5%8D%97,%E8%BF%AA%E5%BA%86%E5%B7%9E,china,diqing,prc,yunnan,zhongdian","S2CellId":"3724000000000000","result":2419,"accuracy":0.98428345,"title":"IMG_6520"}
{"id":5292937744,"url":"http://farm6.staticflickr.com/5045/5292937744_a2ce2fce59.jpg","path":"ab9/83b/ab983bf9c6c9b5abde5d5848fcd63c.jpg","date":"2010-12-20","year":2010,"month":12,"lon":100.74933,"lat":27.732977,"tags":"china,lugu,lugu+lake,prc,yunnan","S2CellId":"6d39400000000000","result":6841,"accuracy":0.15275821,"title":"IMG_9820"}
{"id":3725575890,"url":"http://farm3.staticflickr.com/2622/3725575890_d5a7796f56.jpg","path":"20d/7fb/20d7fbf1db1df87ff3f61c8422599140.jpg","date":"2009-07-04","year":2009,"month":7,"lon":100.381294,"lat":28.391392,"tags":"%E4%B8%AD%E5%9C%8B,%E4%BA%9E%E4%B8%81,%E5%9B%9B%E5%B7%9D,%E7%A8%BB%E5%9F%8E,china","S2CellId":"4617000000000000","result":2765,"accuracy":0.04582896,"title":"%E4%BA%9E%E4%B8%81%E4%B8%89%E7%A5%9E%E5%B1%B1%E2%80%A7%E5%A4%AE%E9%82%81%E5%8B%87"}
{"id":507202512,"url":"http://farm1.staticflickr.com/192/507202512_e23ec24270.jpg","path":"c76/e2f/c76e2f90acfaf590b0afcb956769121c.jpg","date":"2006-04-01","year":2006,"month":4,"lon":100.2832,"lat":28.381735,"tags":"viola+violante","S2CellId":"470c400000000000","result":3179,"accuracy":0.017024873,"title":"06-Chengde-Beijing-Kunming+-+185.jpg"}
{"id":1799454629,"url":"http://farm3.staticflickr.com/2366/1799454629_9d47c1dcff.jpg","path":"2b3/591/2b3591e97e884420bc3d605916ad2d2a.jpg","date":"2007-10-18","year":2007,"month":10,"lon":100.763084,"lat":27.705187,"tags":"china,luguhu,moo,viajes,yunnan","S2CellId":"4771400000000000","result":3386,"accuracy":0.5481238,"title":"Lugu+Hu+%28lago+Lugu%29","description":"El+lago+Lugu+%28%E6%B3%B8%E6%B2%BD%E6%B9%96+-+l%C3%BAg%C5%AB+h%C3%BA%29%2C+situado+entre+las++provincias+de+Yunnan+y+Sichuan%2C+en+el+suroeste+de+China%2C+es+famoso++por+su+peculiar+paisaje+natural+y+la+%C3%BAnica+cultura+misteriosa+del++grupo+%C3%A9tnico+Mosuo%2C+que+conserva+un+sistema+matriarcal.%0A%0ASe+encuentra+a+2685+metros+sobre+el+nivel+del+mar%2C+y+ocupa+48%2C5+km+cuadrados%2C+siendo+bastante+relevante+la+profundidad%3A+hacia+93%2C5+metros+en+su+punto+m%C3%A1s+profundo.+Est%C3%A1+rodeado+de+grandes+monta%C3%B1as+y+tiene+ocho+islas+y+muchas+bah%C3%ADas+y+playas.%0A%0AEl+lago+se+encuentra+a+270+kil%C3%B3metros+de+la+ciudad+de+Lijiang%2C+y+se+necesitan+casi+siete+horas+de+viaje+por+carretera+para+llegar+al+destino%2C+pues+es+necesario+atravesar+cinco+puertos+de+monta%C3%B1a%2C+pasando+el+m%C3%A1s+alto+de+los+4000+metros+sobre+el+nivel+del+mar."}
{"id":595914611,"url":"http://farm2.staticflickr.com/1232/595914611_0e5bc61f07.jpg","path":"89d/570/89d5701e995a58e3f91d8f8a1a2eb5.jpg","date":"2007-06-10","year":2007,"month":6,"lon":99.7059,"lat":27.819342,"tags":"china,yunnan,zhongdian","S2CellId":"4692b00000000000","result":3014,"accuracy":0.01744049,"title":"Could+You+Please+Drop+Something+Please"}
{"id":5315491666,"url":"http://farm6.staticflickr.com/5161/5315491666_8986757115.jpg","path":"c3f/222/c3f2226cb2fca2b682c0bde9b991d6cb.jpg","date":"2010-12-28","year":2010,"month":12,"lon":100.16244,"lat":27.254608,"tags":"china,prc,tiger+leaping+gorge,yunnan","S2CellId":"3724000000000000","result":2419,"accuracy":0.2019746,"title":"IMG_0103"}
{"id":8002451783,"url":"http://farm9.staticflickr.com/8172/8002451783_dd52ec6a9d.jpg","path":"f92/388/f923883b9941ffdedff8cdc74898d9f0.jpg","date":"2012-07-21","year":2012,"month":7,"lon":99.00703,"lat":28.370558,"tags":"baima+snow+mountains,baimang,china,flower,morina+nepalensis,nature,nature+reserve,plant,yunnan","S2CellId":"47d8f40000000000","result":4466,"accuracy":0.0034339484,"title":"Morina+nepalensis+D+Don"}
{"id":2986425774,"url":"http://farm4.staticflickr.com/3050/2986425774_cc5a2191f0.jpg","path":"3a5/5d1/3a55d1d0bae8cd2b9dddaf4aeeea3f9e.jpg","date":"2008-10-17","year":2008,"month":10,"lon":99.77783,"lat":27.592283,"tags":"chine,gorge+du+saut+du+tigre","S2CellId":"39b0000000000000","result":2485,"accuracy":0.30831954,"title":"P1010912"}
{"id":507231297,"url":"http://farm1.staticflickr.com/200/507231297_710001534b.jpg","path":"ee8/50e/ee850ebb8e58daaac1f2dc0e7ad5a.jpg","date":"2006-03-29","year":2006,"month":3,"lon":100.2832,"lat":28.381735,"tags":"viola+violante","S2CellId":"9450000000000000","result":9674,"accuracy":0.017761609,"title":"06-Chengde-Beijing-Kunming+-+157.jpg"}
{"id":2986369368,"url":"http://farm4.staticflickr.com/3066/2986369368_cd4978a0b8.jpg","path":"943/19f/94319faae5a74454e547fcc8123d157.jpg","date":"2008-10-17","year":2008,"month":10,"lon":99.77783,"lat":27.592283,"tags":"chine,gorge+du+saut+du+tigre","S2CellId":"39b0000000000000","result":2485,"accuracy":0.1946879,"title":"P1010851"}
{"id":507214022,"url":"http://farm1.staticflickr.com/231/507214022_2edd4d9717.jpg","path":"55e/be6/55ebe6f97d57a752f0e52d3c60ac29.jpg","date":"2006-04-23","year":2006,"month":4,"lon":100.2832,"lat":28.381735,"tags":"viola+violante","S2CellId":"35f052f000000000","result":2371,"accuracy":0.01829646,"title":"06-Chengde-Beijing-Kunming+-+337.jpg"}
{"id":3768816411,"url":"http://farm3.staticflickr.com/2599/3768816411_e04e6d6485.jpg","path":"435/352/435352adefdac1de81558cfdccd388a4.jpg","date":"2009-07-09","year":2009,"month":7,"lon":99.29921,"lat":28.242086,"tags":"%E4%B8%AD%E5%9C%8B,%E4%B8%AD%E7%94%B8,%E5%BE%B7%E6%AC%BD,%E9%A6%99%E6%A0%BC%E9%87%8C%E6%8B%89,china,shangri-la","S2CellId":"355ab00000000000","result":2274,"accuracy":0.08267769,"title":"%E5%A5%94%E5%AD%90%E6%AC%84%E7%A8%85%E5%8B%99%E5%B1%80%E5%BE%88%E5%B0%8F%E7%9A%84%E5%A4%A7%E9%96%80"}
{"id":1800507764,"url":"http://farm3.staticflickr.com/2083/1800507764_dc9f8dfc78.jpg","path":"28f/48b/28f48bacbd4ede4f4c19aa2c9ab5a086.jpg","date":"2007-10-18","year":2007,"month":10,"lon":100.75025,"lat":27.730375,"tags":"china,luguhu,viajes,yunnan","S2CellId":"12a6f00000000000","result":767,"accuracy":0.45021492,"title":"Lugu+Hu+%28lago+Lugu%29","description":"El+lago+Lugu+%28%E6%B3%B8%E6%B2%BD%E6%B9%96+-+l%C3%BAg%C5%AB+h%C3%BA%29%2C+situado+entre+las++provincias+de+Yunnan+y+Sichuan%2C+en+el+suroeste+de+China%2C+es+famoso++por+su+peculiar+paisaje+natural+y+la+%C3%BAnica+cultura+misteriosa+del++grupo+%C3%A9tnico+Mosuo%2C+que+conserva+un+sistema+matriarcal.%0A%0ASe+encuentra+a+2685+metros+sobre+el+nivel+del+mar%2C+y+ocupa+48%2C5+km+cuadrados%2C+siendo+bastante+relevante+la+profundidad%3A+hacia+93%2C5+metros+en+su+punto+m%C3%A1s+profundo.+Est%C3%A1+rodeado+de+grandes+monta%C3%B1as+y+tiene+ocho+islas+y+muchas+bah%C3%ADas+y+playas.%0A%0AEl+lago+se+encuentra+a+270+kil%C3%B3metros+de+la+ciudad+de+Lijiang%2C+y+se+necesitan+casi+siete+horas+de+viaje+por+carretera+para+llegar+al+destino%2C+pues+es+necesario+atravesar+cinco+puertos+de+monta%C3%B1a%2C+pasando+el+m%C3%A1s+alto+de+los+4000+metros+sobre+el+nivel+del+mar."}
{"id":7986856698,"url":"http://farm9.staticflickr.com/8448/7986856698_f698380771.jpg","path":"264/773/26477374c0a9b5a785b51e64ba3df51.jpg","date":"2012-04-27","year":2012,"month":4,"lon":100.3015,"lat":29.017454,"tags":"china,daocheng,sichuan","S2CellId":"488ed00000000000","result":5771,"accuracy":0.08387749,"title":"Daocheng%2C+Sichuan"}
{"id":5445316808,"url":"http://farm6.staticflickr.com/5254/5445316808_560f17af22.jpg","path":"8e1/f88/8e1f8887904d49fcf502ac584b03810.jpg","date":"2011-01-05","year":2011,"month":1,"lon":100.750656,"lat":27.730164,"tags":"%E5%BD%BC%E5%B2%B8,%E7%80%98%E6%B2%BD%E6%B9%96,%E9%87%8C%E6%A0%BC,dog,lugu+lake,throw+and+catch","S2CellId":"30d4000000000000","result":1622,"accuracy":0.028930774,"title":"%E4%BD%A0%E4%B8%9F%E6%88%91%E6%92%BF","description":"%E5%BD%BC%E5%B2%B8%28%E5%AE%A2%E6%A3%A7%29%E9%A4%8A%E4%BA%86%E5%9B%9B%E6%A2%9D%E5%90%8C%E6%A8%A3%E5%93%81%E7%A8%AE%E7%9A%84%E7%8B%97%EF%BC%8C%E5%85%B6%E4%B8%AD%E6%9C%89%E4%B8%80%E9%9A%BB%E7%89%B9%E5%88%A5%E5%96%9C%E6%AD%A1%E5%8F%BC%E6%9D%B1%E8%A5%BF%E4%BE%86%E6%89%BE%E4%BA%BA%E7%8E%A9%E4%BD%A0%E4%B8%9F%E6%88%91%E6%92%BF%E7%9A%84%E9%81%8A%E6%88%B2%E3%80%82"}
{"id":5141397019,"url":"http://farm5.staticflickr.com/4049/5141397019_5090e77754.jpg","path":"9ee/b98/9eeb98b2ecd74693b564bd5fd60da42.jpg","date":"2010-07-09","year":2010,"month":7,"lon":99.52394,"lat":28.043955,"tags":"55mm+equivalent,chicken+temple,prayer+flags,shangri-la,tibet","S2CellId":"87e5000000000000","result":8030,"accuracy":0.010341498,"title":"Chicken+Temple+cow","description":"Is+it+a+holy+cow%2C+or+does+it+just+like+the+sweet+grass+of+chicken+temple%3F"}
{"id":6765121245,"url":"http://farm8.staticflickr.com/7166/6765121245_1aab682762.jpg","path":"fca/776/fca776705c52bcb8791d232bd3268d6.jpg","date":"2011-09-06","year":2011,"month":9,"lon":99.61304,"lat":28.758028,"tags":"china,jade+dragon+snow+mountain,lijiang.+yunnan,snow+mountain","S2CellId":"5353000000000000","result":6037,"accuracy":0.025959121,"title":"The+Jade+Dragon","description":"Jade+Dragon+Snow+Mountain"}
{"id":7635091714,"url":"http://farm8.staticflickr.com/7264/7635091714_a7bb80f49d.jpg","path":"495/9e3/4959e3c15d14a1837b9cd839541b14.jpg","date":"2012-07-03","year":2012,"month":7,"lon":99.80048,"lat":28.933004,"tags":"%E4%B9%A1%E5%9F%8E,%E5%9B%9B%E5%B7%9D,%E7%94%98%E5%AD%9C%E5%B7%9E,china,prc,sichuan,xiangcheng","S2CellId":"3770000000000000","result":2436,"accuracy":0.2564147,"title":"IMG_6847"}
{"id":5179936944,"url":"http://farm5.staticflickr.com/4108/5179936944_e1cf3deb0d.jpg","path":"ad3/2b0/ad32b04e921fc1f1a0bdd9465d74aef.jpg","date":"2010-10-18","year":2010,"month":10,"lon":99.70403,"lat":27.815731,"tags":"china,gandensumtselingmonastery,shangrila,yunnan","S2CellId":"3770000000000000","result":2436,"accuracy":0.28270683,"title":"monastery+disapointments","description":"no+super+cool+chanting+monks...+but+a+lot+of+stuff+for+sale%2C+under+construction+and+cold+cold+rain..."}
{"id":186802259,"url":"http://farm1.staticflickr.com/45/186802259_be9dc0257d.jpg","path":"f62/df2/f62df21f994a32fd654ab7d2d167a58.jpg","date":"2004-03-31","year":2004,"month":3,"lon":99.94606,"lat":27.5935,"tags":"shangri-la,yunnan","S2CellId":"8715000000000000","result":7727,"accuracy":0.018401472,"title":"Yunnan-007+Shangri-La","description":"Shangri-La+terrain"}
{"id":507242603,"url":"http://farm1.staticflickr.com/201/507242603_1f54c540f1.jpg","path":"a5d/420/a5d4201c3ecfbf596ce7396c8af6bda.jpg","date":"2006-04-22","year":2006,"month":4,"lon":100.2832,"lat":28.381735,"tags":"viola+violante","S2CellId":"0d0b000000000000","result":163,"accuracy":0.008488249,"title":"06-Chengde-Beijing-Kunming+-+294.jpg"}
{"id":1807950949,"url":"http://farm3.staticflickr.com/2247/1807950949_5ae12cf7d5.jpg","path":"b51/1a1/b511a128e3c32d5e6e9a239d72b5a16.jpg","date":"2007-10-04","year":2007,"month":10,"lon":101.18179,"lat":28.44111,"tags":"%E4%B8%AD%E5%9B%BD,%E5%9B%9B%E5%B7%9D,%E6%9C%A8%E9%87%8C,%E9%A3%8E%E5%85%89,china,nature,sichuan","S2CellId":"6001ab0000000000","result":6419,"accuracy":0.07127549,"title":"Untitled"}
{"id":7642036440,"url":"http://farm8.staticflickr.com/7109/7642036440_c64005f3b0.jpg","path":"99b/f3f/99bf3f4adf3a2a69cd25facac712615.jpg","date":"2012-07-23","year":2012,"month":7,"lon":99.00887,"lat":28.354546,"tags":"baima+snow+mountains,baimang,china,flower,nature,nature+reserve,plant,yunnan","S2CellId":"87c5000000000000","result":7979,"accuracy":0.006730688,"title":"Flowers+on+an+old+log","description":"In+Baima+Snow+Mountain+nature+reserve%2C+Yunnan%2C+China."}
{"id":1920005888,"url":"http://farm3.staticflickr.com/2124/1920005888_fa86ed7f48.jpg","path":"fdd/b51/fddb51925426a6c580fc4fb9e7b3cd53.jpg","date":"2007-10-09","year":2007,"month":10,"lon":100.17612,"lat":29.158367,"tags":"%E5%B0%BC%E5%BA%B7,%E7%99%BD%E9%A9%AC%E9%B8%A1,%E7%A8%BB%E5%9F%8E,%E8%91%97%E6%9D%B0%E5%AF%BA,crossoptilon+crossoptilon,d80,daocheng,nikkor,nikon,white-eared+pheasant,zhujie+temple","S2CellId":"14bec00000000000","result":1282,"accuracy":0.051430523,"title":"%E8%91%97%E6%9D%B0%E5%AF%BA%E7%99%BD%E9%A9%AC%E9%B8%A1+-+A+LaMa+was+Feeding+White-eared+Pheasant+at+ZhuJie+Temple","description":"As+stated+at+wikipedia%3A+%3Ci%3EThe+Szechuan+%3Ca+href%3D%22http%3A%2F%2Fen.wikipedia.org%2Fwiki%2FWhite-eared_Pheasant%22%3EWhite-eared+Pheasant%3C%2Fa%3E%2C+Crossoptilon+crossoptilon+crossoptilon%2C+is+a+galliform+bird+native+to+the+Szechuan+region+of+China.+It+is+a+subspecies+of+White-eared+Pheasant%2C+Crossoptilon+crossoptilon.%3C%2Fi%3E"}
{"id":22619600,"url":"http://farm1.staticflickr.com/18/22619600_070c093352.jpg","path":"3a2/16a/3a216acfe092f51894fc8055d6453b5.jpg","date":"2005-06-12","year":2005,"month":6,"lon":100.1572,"lat":27.25502,"tags":"china,river,yunnan","S2CellId":"3724000000000000","result":2419,"accuracy":0.34220272,"title":"Tiger+Leaping+Gorge","description":"See+where+the+photo+was+taken+at+%3Ca+href%3D%22http%3A%2F%2Fmaps.yuan.cc%2F%22+rel%3D%22nofollow%22%3Emaps.yuan.cc%2F%3C%2Fa%3E."}
{"id":7962778630,"url":"http://farm9.staticflickr.com/8295/7962778630_72907cac7c.jpg","path":"f79/944/f799447a6ceb16cac81eb078ee1e1031.jpg","date":"2012-04-21","year":2012,"month":4,"lon":100.0587,"lat":27.15821,"tags":"chang,china,jiang,mountains,river,tiger+leaping+gorge,yangtze,yunnan","S2CellId":"3724000000000000","result":2419,"accuracy":0.3112532,"title":"Yangtze+river%2C+Yunnan"}
{"id":2725054664,"url":"http://farm4.staticflickr.com/3117/2725054664_d612aa7d02.jpg","path":"627/cf1/627cf1e8b62a11bac6bc63f6d828294.jpg","date":"2008-07-31","year":2008,"month":7,"lon":100.78333,"lat":27.7,"tags":"china,lugu+lake","S2CellId":"5470000000000000","result":6094,"accuracy":0.080767035,"title":"Lugu+Lake+and+around+12","description":"Follow+my+travels+online+at+%3Ca+href%3D%22http%3A%2F%2Ftravel.beiske.com%22+rel%3D%22nofollow%22%3Etravel.beiske.com%3C%2Fa%3E"}
{"id":4037391811,"url":"http://farm3.staticflickr.com/2549/4037391811_e530c3b107.jpg","path":"994/2f5/9942f55a6dbea1b43e7c0804fb839a.jpg","date":"2008-05-17","year":2008,"month":5,"lon":99.98803,"lat":27.314857,"tags":"archiv,buddhismus,china,dali,facebook,free,google,holiday,image,images,kloster,landscape,landschaft,lhasa,lijiang,m%C3%B6nch,news,newspaper,nikon,open,pics,pictures,reisen,sect,sekte,shangri-la,source,tempel,temple,tibet,travel,yunnan,zeitung","S2CellId":"3724000000000000","result":2419,"accuracy":0.32566714,"title":"China"}
