{"id":3447620681,"url":"http://farm4.staticflickr.com/3584/3447620681_5869f864b3.jpg","path":"5a1/66b/5a166b140cf19f334355a48551865a4.jpg","date":"2009-03-21","year":2009,"month":3,"lon":146.02478,"lat":-31.475525,"tags":"2009,australia,barrier,cobar,highway,nsw,southern,trangie,western","S2CellId":"6ad1000000000000","result":6610,"accuracy":0.04708987,"title":"Cheapside+Butchery","description":"Not+sure+if+I+want+Carcass+or+small+goods%0A%0A%3Ca+href%3D%22http%3A%2F%2Fwww.cobar.nsw.gov.au%2F%22%3Ewww.cobar.nsw.gov.au%2F%3C%2Fa%3E"}
