{"id":3421212680,"url":"http://farm4.staticflickr.com/3657/3421212680_1818738a63.jpg","path":"2c7/f7f/2c7f7f274e71b557b93dbbde3779dcc.jpg","date":"2009-04-04","year":2009,"month":4,"lon":-5.771362,"lat":41.8111,"tags":"castilla-le%C3%B3n,espa%C3%B1a,granja+de+moreruela,zamora","S2CellId":"144c000000000000","result":1197,"accuracy":0.079551995,"title":"Monasterio+de+Moreruela+-+Marcas+de+cantero"}
{"id":5187104626,"url":"http://farm2.staticflickr.com/1275/5187104626_a0e3a67124.jpg","path":"5bd/b59/5bdb5922c3b43cffd31bc9461fc616c.jpg","date":"2010-03-11","year":2010,"month":3,"lon":-5.583801,"lat":41.007835,"tags":"redes,sociedaddelainformaci%C3%B3n,tdt","S2CellId":"185c000000000000","result":1431,"accuracy":0.010989556,"title":"Plan+nacional+de+transici%C3%B3n+a+la+TDT+2010+%28Castellanos+de+Moriscos%29","description":"Im%C3%A1genes+de+las+acciones+desarrolladas+durante+el+2010+dentro+del+plan+nacional+de+transici%C3%B3n+a+la+TDT."}
{"id":5600395040,"url":"http://farm6.staticflickr.com/5228/5600395040_6db12e20d6.jpg","path":"a79/dda/a79dda4aef3445fe5ad6f57936181ba6.jpg","date":"2009-09-07","year":2009,"month":9,"lon":-5.749294,"lat":41.501217,"tags":"plandetransici%C3%B3nalatdt,redes,sociedaddelainformaci%C3%B3n,tdt","S2CellId":"94ce59f000000000","result":9723,"accuracy":0.01910573,"title":"II+Fase+del+Plan+de+Transici%C3%B3n+a+la+TDT+-+Ayuntamientos%2C+07%2F09%2F2009%2C+%28Zamora%29","description":"Plan+de+acci%C3%B3n+del+Ministerio+de+Industria%2C+Turismo+y+Comercio+con+el+objetivo+de+acercar+la+TDT+e+informar+del+cese+anal%C3%B3gico+a+la+ciudadan%C3%ADa."}
{"id":81480059,"url":"http://farm1.staticflickr.com/38/81480059_2f3b451971.jpg","path":"e26/6fb/e266fbc0f984c749355a7fbd17d16055.jpg","date":"2005-12-30","year":2005,"month":12,"lon":-5.535907,"lat":41.043755,"tags":"abigfave,anais,cielo,escenas,explore,geometrias,lineas,mholm,paisaje,personas,solos,viajes","S2CellId":"0d39000000000000","result":327,"accuracy":0.18200912,"title":"esperando+al+tren"}
{"id":3808934888,"url":"http://farm3.staticflickr.com/2596/3808934888_83cf1799e7.jpg","path":"60b/9c5/60b9c5199fb1a23cbf59bbe16d79ba77.jpg","date":"2009-08-10","year":2009,"month":8,"lon":-5.987548,"lat":41.533253,"tags":"casta%C3%B1ar,comarcas,espa%C3%B1a,europa,europe,leonese+country,leonese+region,lli,oestepurpura,pa%C3%ADs+leon%C3%A9s,pa%C3%ADs+llion%C3%A9s,regi%C3%B3n+leonesa,rex%C3%B3n+llionesa,salamanca,spain","S2CellId":"15c3000000000000","result":1406,"accuracy":0.007579833,"title":"Casta%C3%B1ar","description":"Casta%C3%B1ar"}
{"id":3144879119,"url":"http://farm4.staticflickr.com/3262/3144879119_9030810a95.jpg","path":"df2/479/df2479b5539a3913917d1d81eaf848.jpg","date":"2008-12-28","year":2008,"month":12,"lon":-5.681058,"lat":41.995144,"tags":"benavente,california,comida,food,restaurant,restaurante,zamora","S2CellId":"3442ae9000000000","result":2087,"accuracy":0.029889582,"title":"Congrio+al+Ajo+Arriero","description":"Ver+art%C3%ADculo+en+mi+Blog+en+%3Ca+href%3D%22http%3A%2F%2Fwww.ellaboratoriogastronomico.com%2F2008%2F12%2F29%2Frestaurante-california%2F%22+target%3D%22_blank%22%3EEnlace%3C%2Fa%3E%0ASee+post+in+My+blog+at+%3Ca+href%3D%22http%3A%2F%2Fwww.ellaboratoriogastronomico.com%2F2008%2F12%2F29%2Frestaurante-california%2F%22+target%3D%22_blank%22%3ELink%3C%2Fa%3E"}
{"id":3021523827,"url":"http://farm4.staticflickr.com/3073/3021523827_5012e06ab9.jpg","path":"1b8/967/1b89679bdba19f696cd0725ee7ce755.jpg","date":"2008-11-11","year":2008,"month":11,"lon":-5.748274,"lat":41.503235,"tags":"%C3%A9p%C3%ADt%C3%A9szet,%CE%B1%CF%81%CF%87%CE%B9%CF%84%CE%B5%CE%BA%CF%84%CE%BF%CE%BD%CE%B9%CE%BA%CE%AE,%D0%B0%D1%80%D1%85%D0%B8%D1%82%D0%B5%D0%BA%D1%82%D1%83%D1%80%D0%B0,%E5%BB%BA%E7%AF%89,architecture,architectuur,architektur,architettura,arhitektura,arkitekt%C3%BAr,arkitektur,arkitektura,arkitekturen,arkkitehtuuri,arquitectura,arquitectura+moderna,arquitetura,building,castilla,castilla+y+leon,ekain,ekainj,etnografia,etnografico,modern,modern+architecture,moderna,moderno,museo,museum,pic,zamora","S2CellId":"548ff00000000000","result":6177,"accuracy":0.010371031,"title":"Museo+Etnogr%C3%A1fico+de+Castilla+y+Le%C3%B3n%2C+Zamora"}
{"id":1306007363,"url":"http://farm2.staticflickr.com/1287/1306007363_6ac7f81e67.jpg","path":"408/b98/408b98a75825a6a56d4d354c35ca6328.jpg","date":"2006-07-02","year":2006,"month":7,"lon":-5.747973,"lat":41.502342,"tags":"ceramica,cerdo,coolpix2000,espa%C3%B1a,hucha,nikon,pig,piggybank,spain,terracotta,zamora","S2CellId":"95bcca4000000000","result":9843,"accuracy":0.031101895,"title":"Huchas+%2F+Piggy+Banks","description":"Zamora%2C+2%2F7%2F2006.+As%C3%AD+eran+los+cerditos+del+a%C3%B1o+pasado+%3B-%29+.%0A%0AThese+were+last+year%27s+piggy+banks."}
{"id":854780954,"url":"http://farm2.staticflickr.com/1401/854780954_d7e20dc02a.jpg","path":"a2c/4a2/a2c4a2ddc2ff5aa547f6726de3c6a7d.jpg","date":"2007-06-28","year":2007,"month":6,"lon":-5.747973,"lat":41.502342,"tags":"100vistas,ach%C3%BAuuuuuuuuu%21%21%21%21%21%21%21%21%21%21%21%21%21%21%21%21%21%21,ceramica,cerditos,cerdo,coolpix2000,espa%C3%B1a,hucha,insisto.en.q.mas.q.alcanc%C3%ADas,little,me.das.sal%3F,nikon,parecen.saleros%21,pig,piggybank,spain,terracotta,three,tres,zamora","S2CellId":"95bcca4000000000","result":9843,"accuracy":0.027554067,"title":"Los+tres+cerditos+%2F+Three+Little+Pigs","description":"Zamora%2C+28%2F6%2F2007.+Huchas+con+forma+de+cerdito+%28premio+para+el+que+adivine+cu%C3%A1nto+cuestan+%3A-P+%29.+Tomada+en+la+Feria+de+Cer%C3%A1mica+y+Alfarer%C3%ADa+Popular+celebrada+durante+las+fiestas+de+San+Pedro.%0A%0AExplore+%28%23330%29+el+13%2F10%2F2008."}
{"id":1337439009,"url":"http://farm2.staticflickr.com/1014/1337439009_2231ea3c06.jpg","path":"fe1/db5/fe1db514b474d21b1a5ee96eb6a74c8.jpg","date":"2007-07-03","year":2007,"month":7,"lon":-5.10125,"lat":41.730274,"tags":"espa%C3%B1a,monasterio,santa+espina,spain,valladolid","S2CellId":"12b6700000000000","result":815,"accuracy":0.03623717,"title":"Monasterio+de+la+Santa+Espina","description":"Sala+Capitular"}
{"id":2534173797,"url":"http://farm4.staticflickr.com/3028/2534173797_67b290ef97.jpg","path":"52e/03b/52e03bb3edbfb522a113df4ce4295c8.jpg","date":"2008-05-29","year":2008,"month":5,"lon":-5.747737,"lat":41.50099,"tags":"catedral,de,espa%C3%B1a,hierro,nocturnas,piedra,puente,vistas,zamora,zamoranos","S2CellId":"0d39000000000000","result":327,"accuracy":0.2602972,"title":"Zamora%2C+Puente+de+Piedra"}
{"id":3420416733,"url":"http://farm4.staticflickr.com/3554/3420416733_02f924665f.jpg","path":"ddc/09c/ddc09c8ddb80feb958c166c3ee5e149a.jpg","date":"2009-04-04","year":2009,"month":4,"lon":-5.771362,"lat":41.8111,"tags":"castilla-le%C3%B3n,espa%C3%B1a,granja+de+moreruela,zamora","S2CellId":"398c000000000000","result":2482,"accuracy":0.06453453,"title":"Monasterio+de+Moreruela+-+Detalle"}
{"id":7568052404,"url":"http://farm9.staticflickr.com/8156/7568052404_0ff080c66c.jpg","path":"199/a4f/199a4fe4402e1bdfca52f68ce8156b62.jpg","date":"2012-07-13","year":2012,"month":7,"lon":-5.368881,"lat":41.65644,"tags":"366,366+days,366+dias,366+i%C3%B1aki+perez,366dias366fotos,dias,fotos,i%C3%B1aki,i%C3%B1aki+p%C3%A9rez,i%C3%B1aki+perez+fotografia,perez,proyecto+366,proyecto+de+i%C3%B1aki+perez","S2CellId":"0d39000000000000","result":327,"accuracy":0.0149498535,"title":"194%2F366+%C2%B7+Atardece+en+Vezdemarban","description":"Como+era+de+esperar%2C+nada+mas+llegar+al+pueblo%2C+he+cogido+la+c%C3%A1mara+y+me+he+subido+a+la+colina+a+hacer+algunas+fotillos+del+atardecer%2C+el+%C3%BAnico+problema%2C+que+era+demasiado+pronto+y+el+sol+a%C3%BAn+estaba+muy+alto.+A+la+noche%2C+hemos+ido+a+ver+si+caz%C3%A1bamos+las+estrellas+y+hacer+algo+de+fotograf%C3%ADa+nocturna%2C+pero+entre+que+hemos+ido+con+prisas+y+mi+iterval%C3%B3metro+me+da+problemas+desde+hace+ya+tiempo+no+me+ha+dado+tiempo+mas+que+para+hacer+una+mediocridad+de+4+minutos.+Ma%C3%B1ana+intentare+hacer+m%C3%A1s+y+mejor.+Mientras+tanto+os+dejo+con+estas+bonitas+nubes.+Hasta+ma%C3%B1ana.%0A%0A%3Ca+href%3D%22http%3A%2F%2F366dias366fotos.wordpress.com%2F2012%2F07%2F13%2F194366-%25C2%25B7-atardece-en-vezdemarban%2F%22+rel%3D%22nofollow%22%3E366dias366fotos.wordpress.com%2F2012%2F07%2F13%2F194366-%25C2%25B7-at...%3C%2Fa%3E"}
{"id":4494364936,"url":"http://farm3.staticflickr.com/2735/4494364936_5ff7feb36e.jpg","path":"71e/327/71e32750a31efc71846d6f83ea96187e.jpg","date":"2010-04-02","year":2010,"month":4,"lon":-5.146204,"lat":41.196697,"tags":"castilla-le%C3%B3n,espa%C3%B1a,fresno+el+viejo,valladolid","S2CellId":"0d6a0c0000000000","result":555,"accuracy":0.09718006,"title":"Iglesia+de+San+Juan+Bautista+-+Interior+2"}
{"id":6142357918,"url":"http://farm7.staticflickr.com/6075/6142357918_2620857d58.jpg","path":"71e/2c9/71e2c9c74043d1803da6047fd5edf91.jpg","date":"2010-07-24","year":2010,"month":7,"lon":-5.740023,"lat":41.507816,"tags":"a720,arbol,azul,blue,canon,cielo,espa%C3%B1a,gettyimagesiberiaq3,green,landscape,paint.net,paisaje,powershot,puntodefuga,sky,spain,tree,urban,urbano,vanishingpoint,verde,zamora","S2CellId":"0d418c0000000000","result":341,"accuracy":0.046283375,"title":"Fuga+veraniega+%2F+Vanshing+summer","description":"%3Cb%3EZamora%2C+24%2F7%2F2010.%3C%2Fb%3E"}
{"id":5870125539,"url":"http://farm4.staticflickr.com/3209/5870125539_c2f94fa89c.jpg","path":"af7/ef2/af7ef26cce795544ac56cd29b8a6.jpg","date":"2011-06-25","year":2011,"month":6,"lon":-5.157769,"lat":41.81407,"tags":"castilla-le%C3%B3n,espa%C3%B1a,tordehumos,valladolid","S2CellId":"132a540700000000","result":1024,"accuracy":0.024732387,"title":"Iglesia+de+Santa+Mar%C3%ADa+la+Sagrada+-+Lado+izquierdo+del+banco+del+retablo+mayor"}
{"id":482905769,"url":"http://farm1.staticflickr.com/228/482905769_31f8d4029c.jpg","path":"78b/3e3/78b3e3fa453db9579113bb4c825d2fe0.jpg","date":"2005-05-27","year":2005,"month":5,"lon":-5.739283,"lat":41.499256,"tags":"coolpix2000,douro,duero,espa%C3%B1a,landscape,nikon,paisaje,rio,river,spain,zamora","S2CellId":"0d42100000000000","result":347,"accuracy":0.042020563,"title":"Ace%C3%B1as","description":"Zamora%2C+27%2F5%2F2005.+Al+atardecer%2C+junto+a+las+Ace%C3%B1as+de+Pinilla."}
{"id":6254860270,"url":"http://farm7.staticflickr.com/6032/6254860270_affbc7e6fb.jpg","path":"924/d54/924d548acb8a9b27fe59a4867171e3c.jpg","date":"2011-10-15","year":2011,"month":10,"lon":-5.016975,"lat":41.92348,"tags":"canal+de+castilla,castilla+y+le%C3%B3n,espa%C3%B1a,medina+de+rioseco,oto%C3%B1o,pen%C3%ADnsula+ib%C3%A9rica,puente,puente+moral,ramal+de+campo,reflejos,uni%C3%B3n+europea,valladolid,villanueva+de+san+mancio","S2CellId":"0d39000000000000","result":327,"accuracy":0.016731732,"title":"PUENTE+MORAL","description":"DEDICADA+A+ZOA+M%C2%AA.+la+foto+fue+tomada+el+s%C3%A1bado+por+la+tarde.%0ACanal+de+Castilla%2C+Ramal+de+Campos%2C+tiene+siete+esclusas%2C+comienza+en+la+provincia+de+Palencia+en+el+lugar+conocido+como+Calahorra+de+Ribas+y+termina+en+Medina+de+Rioseco.+Aqu%C3%AD+concretamente+est%C3%A1+en+el+t%C3%A9rmino+de+Villanueva+de+San+Mancio%2C+cerca+de+la+septima+esclusa."}
{"id":2351288045,"url":"http://farm4.staticflickr.com/3082/2351288045_ae4a3c79ed.jpg","path":"124/2d9/1242d9ac7adb353b9f5bb4495a4a90.jpg","date":"2008-03-20","year":2008,"month":3,"lon":-5.038722,"lat":41.882385,"tags":"castilla-le%C3%B3n,espa%C3%B1a,medina+de+rioseco,valladolid","S2CellId":"0d41500000000000","result":338,"accuracy":0.03276502,"title":"Arco+del+Aj%C3%BAjar+-+Vista+general"}
{"id":3066409545,"url":"http://farm4.staticflickr.com/3254/3066409545_675bd78050.jpg","path":"60c/35e/60c35ec18c496d112f8a5f713d8bab.jpg","date":"2008-11-01","year":2008,"month":11,"lon":-5.72142,"lat":41.514698,"tags":"a720,arbol,atardecer,azul,black,blue,canon,copa,crown,dusk,espa%C3%B1a,goldstaraward,negro,powershot,silhouette,silueta,spain,the+perfect+photographer,top,tree,zamora","S2CellId":"1296400000000000","result":655,"accuracy":0.009744779,"title":"Melancol%C3%ADa+arb%C3%B3rea+%2F+Tree+Melancholy","description":"Zamora%2C+1%2F11%2F2008.%0A%0AVisita+mi+blog%3A+%3Ca+href%3D%22http%3A%2F%2Ftecnousuario.blogspot.com%2F%22%3Ehttp%3A%2F%2Ftecnousuario.blogspot.com%2F%3C%2Fa%3E"}
{"id":2354833708,"url":"http://farm3.staticflickr.com/2316/2354833708_947d23e07e.jpg","path":"b14/68f/b1468f7948b444f2e4d9e9ca6dd811e.jpg","date":"2008-03-20","year":2008,"month":3,"lon":-5.746536,"lat":41.503242,"tags":"cofrade,costalero,estilomk,k100d,paso,pentax,procesi%C3%B3n,procession,religion,santa,semana,zamora","S2CellId":"809f000000000000","result":7130,"accuracy":0.009732231,"title":"Semana+Santa"}
{"id":3874751458,"url":"http://farm3.staticflickr.com/2535/3874751458_7fc3be3ee7.jpg","path":"ab1/849/ab1849d551ae86f70a946f82a99f2ca.jpg","date":"2009-08-28","year":2009,"month":8,"lon":-5.179667,"lat":41.984936,"tags":"aguilar+de+campos,castilla-le%C3%B3n,espa%C3%B1a,valladolid","S2CellId":"9144000000000000","result":9599,"accuracy":0.115188956,"title":"Iglesia+de+San+Andr%C3%A9s+-+Canecillo+5"}
{"id":6952708432,"url":"http://farm8.staticflickr.com/7138/6952708432_2970c3f9f6.jpg","path":"e37/5f8/e375f80bf260da1a9deec6e68ad718.jpg","date":"2012-04-21","year":2012,"month":4,"lon":-5.000528,"lat":41.499866,"tags":"castilla-le%C3%B3n,espa%C3%B1a,tordesillas,valladolid","S2CellId":"85cfd00000000000","result":7456,"accuracy":0.033462357,"title":"Iglesia+de+San+Antol%C3%ADn+-+Lateral+derecho+del+retablo+de+la+capilla+de+los+Alderete"}
{"id":4744746991,"url":"http://farm5.staticflickr.com/4076/4744746991_228d69f1c2.jpg","path":"758/cb4/758cb48b8c37cf2713a84f6feb88cd2.jpg","date":"2010-06-24","year":2010,"month":6,"lon":-5.745441,"lat":41.503983,"tags":"2010,fiestas,pedro,san,zamora","S2CellId":"12a3840000000000","result":681,"accuracy":0.48688185,"title":"Zamora%2C+Fiestas+de+San+Pedro"}
{"id":2621043987,"url":"http://farm4.staticflickr.com/3283/2621043987_4ed7261752.jpg","path":"8ae/05b/8ae05bd76ee2adbcb3dcb1b09dfb5fb5.jpg","date":"2008-06-28","year":2008,"month":6,"lon":-5.204601,"lat":41.727158,"tags":"%E2%88%97franja,e300,elgimp,espa%C3%B1a,europa,europe,franjav4ll,gimp,olympus,softwarelibre,spain,thegimp,urue%C3%B1a,valladolid,verano,vertical","S2CellId":"0d47c00000000000","result":402,"accuracy":0.07100148,"title":"Palomar+Urue%C3%B1a"}
{"id":836404077,"url":"http://farm2.staticflickr.com/1255/836404077_b9548153a6.jpg","path":"7d6/d6e/7d6d6e66fe4f5aa0e92390c2c6e0d92.jpg","date":"2007-07-08","year":2007,"month":7,"lon":-5.535264,"lat":41.03419,"tags":"bull,bw,espantes,explore,fuentesauco,toro","S2CellId":"94cc400000000000","result":9693,"accuracy":0.051953185,"title":"Cultura+popular"}
{"id":2081591831,"url":"http://farm3.staticflickr.com/2241/2081591831_39f42eb7f3.jpg","path":"d4d/d80/d4dd8038b2aad376e5f7616e3b152da3.jpg","date":"2007-11-09","year":2007,"month":11,"lon":-5.733264,"lat":41.499176,"tags":"100vistas,a710,autumn,camino,canon,espa%C3%B1a,gettyimagesiberiaq3,hojas,landscape,leaves,oto%C3%B1o,paisaje,path,powershot,spain,tolkien,zamora","S2CellId":"476a400000000000","result":3321,"accuracy":0.010084781,"title":"El+camino+sigue+y+sigue+%2F+The+Road+Goes+Ever+On","description":"Zamora%2C+9%2F11%2F2007.%0A%0AEl+camino+sigue+y+sigue%0Adesde+la+puerta.%0AEl+camino+ha+ido+muy+lejos%2C%0Ay+si+es+posible+he+de+seguirlo%0Arecorri%C3%A9ndolo+con+pie+decidido%0Ahasta+llegar+a+un+camino+m%C3%A1s+ancho%0Adonde+se+encuentran+senderos+y+cursos.%0A%C2%BFY+de+ah%C3%AD+ad%C3%B3nde+ir%C3%A9%3F+No+podr%C3%ADa+decirlo.%0A%3Ci%3EJ.+R.+R.+Tolkien%2C+El+Se%C3%B1or+de+los+Anillos%3C%2Fi%3E%0A_________________________________________________________________%0A%0AThe+Road+goes+ever+on+and+on%0ADown+from+the+door+where+it+began.%0ANow+far+ahead+the+Road+has+gone%2C%0AAnd+I+must+follow+it%2C+if+I+can%2C%0APursuing+it+with+eager+feet%2C%0AUntil+it+joins+some+larger+way%0AWhere+many+paths+and+errands+meet.%0AAnd+whither+then%3F+I+cannot+say.%0A%3Ci%3EJ.+R.+R.+Tolkien%2C+The+Lord+of+the+Rings%3C%2Fi%3E"}
{"id":9021914895,"url":"http://farm6.staticflickr.com/5464/9021914895_81095a5d24.jpg","path":"1a7/3c0/1a73c0e262e4e176f942bca441c3f.jpg","date":"2013-06-12","year":2013,"month":6,"lon":-5.467758,"lat":41.33377,"tags":"castillayle%C3%B3n,el,elpego,pego,zamora","S2CellId":"398c000000000000","result":2482,"accuracy":0.022951517,"title":"El+Pego+2"}
{"id":8373661153,"url":"http://farm9.staticflickr.com/8184/8373661153_1508337f6f.jpg","path":"b21/f48/b21f48886eeda62839ff3798a4becc2.jpg","date":"2012-12-29","year":2012,"month":12,"lon":-5.590662,"lat":41.805626,"tags":"ajena,cielos,rural,vistas","S2CellId":"4871500000000000","result":5036,"accuracy":0.03928321,"title":"Tierra+de+Campos"}
{"id":5871695117,"url":"http://farm7.staticflickr.com/6040/5871695117_6d259dcdb2.jpg","path":"f96/73b/f9673bc4a4e1d48a9ff9837bb4328d4e.jpg","date":"2011-06-25","year":2011,"month":6,"lon":-5.097602,"lat":41.945847,"tags":"berrueces,castilla-le%C3%B3n,espa%C3%B1a,valladolid","S2CellId":"85cfd00000000000","result":7456,"accuracy":0.040734086,"title":"Iglesia+de+San+Pedro+-+Retablo+lateral+2"}
{"id":7098756337,"url":"http://farm8.staticflickr.com/7046/7098756337_39c3b4503f.jpg","path":"f81/d3e/f81d3e052a2ef52e9ab265470609de7.jpg","date":"2012-04-21","year":2012,"month":4,"lon":-5.000528,"lat":41.499866,"tags":"castilla-le%C3%B3n,espa%C3%B1a,tordesillas,valladolid","S2CellId":"85cfd00000000000","result":7456,"accuracy":0.03847365,"title":"Iglesia+de+San+Antol%C3%ADn+-+Llanto+sobre+Cristo+muerto%2C+atribuido+a+Juan+de+Ortiz"}
{"id":5526156321,"url":"http://farm6.staticflickr.com/5257/5526156321_37f419fe99.jpg","path":"5e6/aef/5e6aef4c1cbe8a1d4994b2892abb63d1.jpg","date":"2011-02-26","year":2011,"month":2,"lon":-5.756009,"lat":41.50007,"tags":"castilla-le%C3%B3n,espa%C3%B1a,zamora","S2CellId":"132e900000000000","result":1057,"accuracy":0.09048203,"title":"Catedral+-+Vista+nocturna+desde+el+Castillo"}
{"id":1270939562,"url":"http://farm2.staticflickr.com/1130/1270939562_0d5bf2a73e.jpg","path":"f09/e75/f09e751895136be933d4721b4c6df96.jpg","date":"2007-08-20","year":2007,"month":8,"lon":-5.002899,"lat":41.501698,"tags":"tordesillas,vacaciones","S2CellId":"0d39000000000000","result":327,"accuracy":0.008957087,"title":"Viaje+a+Oporto+337"}
{"id":2931026651,"url":"http://farm4.staticflickr.com/3059/2931026651_2aac502d8a.jpg","path":"539/c6d/539c6d296165458be084fa6b159e667b.jpg","date":"2008-10-11","year":2008,"month":10,"lon":-5.005645,"lat":41.503407,"tags":"castile+and+le%C3%B3n,castilla+y+le%C3%B3n,erasmus+students,germans,tordesillas","S2CellId":"0d6a0c0000000000","result":555,"accuracy":0.08814434,"title":"German+students+at+Tordesillas"}
{"id":5514635439,"url":"http://farm6.staticflickr.com/5100/5514635439_36a35dabc0.jpg","path":"3e1/381/3e1381a5b20705a4be49b2ab481109c.jpg","date":"2010-08-10","year":2010,"month":8,"lon":-5.739873,"lat":41.50036,"tags":"duero,espa%C3%B1a,r%C3%ADo,river,spain,zamora","S2CellId":"0d39000000000000","result":327,"accuracy":0.056500666,"title":"Duero+river+%2F+R%C3%ADo+Duero","description":"Zamora.%0A%0ASome+pics+taken+last+summer.%0AAlgunas+fotos+hechas+el+verano+pasado."}
{"id":3409355593,"url":"http://farm4.staticflickr.com/3352/3409355593_123621ebbc.jpg","path":"487/d4c/487d4c2ef68bb0d978f30917c985d38.jpg","date":"2009-03-30","year":2009,"month":3,"lon":-5.972957,"lat":41.40173,"tags":"antonio+guill%C3%A9n,ciliado,ciliate,ciliophora,fotograf%C3%ADa+microsc%C3%B3pica,fotograf%C3%ADas+microsc%C3%B3picas,hipotrico,hypotrichida,ies+batalla+de+clavijo,im%C3%A1genes+microsc%C3%B3picas,la+vida+oculta+del+agua,microfotograf%C3%ADa,microorganismos,microphotography,microscopio,microscopy,photomicrography,pond+life,protozoa,protozoo,proyecto+agua,sayago,sogo,spain,the+life+hidden+of+the+water,urosoma,vida+oculta,vida+oculta+del+agua,zamora","S2CellId":"47abc00000000000","result":3957,"accuracy":0.011609784,"title":"EL+COMPORTAMIENTO+DE+UROSOMA","description":"Si+tuvi%C3%A9semos+que+describir+a+este+ciliado+observando++sus+movimientos%2C+dir%C3%ADamos+que+es+un+protozoo+nervioso%2C+bastante+impulsivo+y%2C+desde+luego%2C+imprevisible.+Apenas+se+detiene+un+instante+y+sus+movimientos%2C+r%C3%A1pidos%2C+casi+como+saltos%2C+hacen+que+se+desplace+hacia+adelante+e+inmediatamente+despu%C3%A9s+hacia+atr%C3%A1s%2C+o+todav%C3%ADa+m%C3%A1s+hacia+adelante%2C+tambi%C3%A9n+puede+irse+hacia+un+lado...o+al+contrario%2C+pero+puede+dar+un+giro+repentino+y+desaperecer+de+nuestra+vista.+Es%2C+como+se%C3%B1al%C3%A1bamos+antes+totalmente+imprevisible.+Le+gusta+enconderse+entre+los+detritus+que+se+encuentran+en+el+fondo+del+agua%2C+sobre+todo+ente+restos+de+algas+de+los+que+se+alimenta+sin+desaprovechar%2C+si+se+le+presenta+la+ocasi%C3%B3n%2C+tomarse+un+peque%C3%B1o+aperitivo+de+algas+verdes.+Urosoma+es+un+ciliado+del+grupo+de+los+hipotricos%2C+tiene+pocos+cilios%2C+con+un+cuerpo+pegado+a+una+cola+o+una+cola+pegada+a+un+cuerpo+sin+que+se+sepa+d%C3%B3nde+empieza+uno+y+finaliza+la+otra.+Su+aspecto+es+algo+amenazante%2C+esos+cilios+tan+agudos+y+anchos+-reciben+el+nombre+de+cirros-+parecen+casi+espinas.+Sin+embargo+nada+m%C3%A1s+lejos+de+la+realidad%2C+quiza+su+aspecto+sea+s%C3%B3lo+una+manera+de+defenderse+en+la+jungla+de+la+gota+de+agua+y+su+nerviosismo+y+movimientos+impredecibles+puedan+salvar+su+vida+en+m%C3%A1s+de+una+ocasi%C3%B3n.%0ALa+fotograf%C3%ADa%2C+realizada+a+400+aumentos+con+la+t%C3%A9cnica+de+contraste+de+interferencia%2C+procede+de+una+muestra+recogida+en+el+arroyo+de+Sogo%2C+en+la+comarca+de+Sayago%2C+Zamora.%0A%0ACon+nuestra+gratitud+para++Antonio+Mart%C3%ADnez+Ron+por+la+rese%C3%B1a+incluida+en+su++excelente+blog+%3Ca+href%3D%22http%3A%2F%2Ffogonazos.blogspot.com%2F2009%2F03%2Fviaje-al-interior-de-una-gota-de-agua.html%22%3EFogonazos%3C%2Fa%3E+de+nuestra+galer%C3%ADa...y+tambi%C3%A9n+a+Paul+por+su+referencia+en+%3Ca+href%3D%22http%3A%2F%2Fwww.dataisnature.com%2F%22%3Ewww.dataisnature.com%2F%3C%2Fa%3E+y+por+su+magn%C3%ADfica+galer%C3%ADa%0A%0APuedes+tener+otra+infomaci%C3%B3n+en+la+exposici%C3%B3n+%3Ca+href%3D%22http%3A%2F%2Fwww.iesbatalladeclavijo.com%2Ftablon%2Fwebvidaoculta%2Findex.html%22%3ELA+VIDA+OCULTA+DEL+AGUA%3C%2Fa%3E%0A%0AY+en+este+%3Ca+href%3D%22http%3A%2F%2Fhttp%3A%2F%2Fwww.iesbatalladeclavijo.com%2Ftablon%2Ffolletooptimizdo.pdf%22%3Ecat%C3%A1logo%3C%2Fa%3E%0A%0ATambi%C3%A9n+en+la+%3Ca+href%3D%22http%3A%2F%2Fwww.fotolog.com%2Fproyectoagua%22%3Egaler%C3%ADa+de+Fotolog%3C%2Fa%3E%0A%0AY+nuestro+granito+de+arena+%3Ca+href%3D%22http%3A%2F%2Fwww.fund-culturadepaz.org%2Fspa%2F03%2Fcent03Articulos+2003%2FEn_pie_de_paz.pdf%22%3Epor+la+Paz%3C%2Fa%3E"}
