{"id":4030823552,"url":"http://farm4.staticflickr.com/3442/4030823552_97f26cfcc6.jpg","path":"1a5/da1/1a5da1ac5f6b8b8f2c218e451ca32c2.jpg","date":"2009-10-17","year":2009,"month":10,"lon":107.55055,"lat":-7.193333,"tags":"blue,cileunca,lake,situ,sky,water","S2CellId":"80da400000000000","result":7308,"accuracy":0.036777534,"title":"Situ+Cileunca%2C+Pengalengan","description":"Regency+of+Bandung%2C+West+Java."}
{"id":4920512527,"url":"http://farm5.staticflickr.com/4137/4920512527_1b0eae5366.jpg","path":"703/44b/70344bc5537958d44f56b3429526c.jpg","date":"2010-07-31","year":2010,"month":7,"lon":107.89759,"lat":-7.059053,"tags":"java,locationinterpolated","S2CellId":"312f000000000000","result":1733,"accuracy":0.056187063,"title":"P1080922.JPG"}
{"id":4921130464,"url":"http://farm5.staticflickr.com/4099/4921130464_5d91afb126.jpg","path":"ae6/272/ae6272ae56ffc3f2b7bb295b2c8e8eb5.jpg","date":"2010-07-31","year":2010,"month":7,"lon":107.888794,"lat":-7.079978,"tags":"java,locationinterpolated","S2CellId":"2e68c00000000000","result":1564,"accuracy":0.024977298,"title":"P1090083.JPG"}
{"id":3865819816,"url":"http://farm3.staticflickr.com/2641/3865819816_8b1be8e773.jpg","path":"603/99c/60399ca88d7457736af2991ecc0d08a.jpg","date":"2009-07-18","year":2009,"month":7,"lon":107.58,"lat":-7.22,"tags":"indonesia,java,malabar+tea+estate,raw","S2CellId":"6b2c000000000000","result":6729,"accuracy":0.016724683,"title":"Malabar+Tea+Estate%2C+the+Malabar+Mess","description":"The+history+of+Malabar+dates+back+to+the+1890+when+the+culture+of+Dutch+began+to+flow+into+the+highland+of+Pangalengan.+Malabar+tea+estate+was+established+in+1896+and+Karel+Albert+Rudolf+Bosscha+was+the+plantation%E2%80%99s+first+manager.+Later+on%2C+he+was+the+General+Manager+to+all+tea+estate+in+the+Pangalengan+region.+During+his+32+years+as+manager+of+the+tea+estate+he+had+accomplished+his+job+enormously.+He+erected+two+tea+factories+in+Malabar%2C+one+was+near+his+residence+also+his+office%2C+called+Malabar+tea+factory+and+the+other+was+erected+later+%281905%29%2C+called+Tanara+%28now+Malabar+tea+factory%29.+The+first+Malabar+tea+factory+is+now+known+as+the+%E2%80%9CSporthall+Gelora+Dinamika%E2%80%9D.++%3Ci%3EFrom+%3Ca+href%3D%22http%3A%2F%2Finfo.bdg.tripod.com%2Fmalabar%2Ftext_01e.htm%22+rel%3D%22nofollow%22%3EMalabar+Tea+Estate%3C%2Fa%3E%3C%2Fi%3E.%0A%0A%3Ca+href%3D%22http%3A%2F%2Fwww.fotopedia.com%2Falbums%2FmrfznaeN-Mc%2Fentries%2FO9lSan-swtY%22+rel%3D%22nofollow%22%3EOther+Malabar+Tea+Estate+pictures%3C%2Fa%3E."}
{"id":10250548235,"url":"http://farm9.staticflickr.com/8418/10250548235_f83984d0fc.jpg","path":"627/e43/627e435532b188b2333105ee1d94020.jpg","date":"2013-09-15","year":2013,"month":9,"lon":107.51512,"lat":-7.135959,"tags":"angry+bird,house,housing,kids,village,villager","S2CellId":"30cc000000000000","result":1621,"accuracy":0.058727276,"title":"Sunday+for+Kid"}
{"id":4052622023,"url":"http://farm3.staticflickr.com/2770/4052622023_46aa7a41ce.jpg","path":"26a/639/26a6392bf9a50d11e67fccb3c36f8a.jpg","date":"2009-10-17","year":2009,"month":10,"lon":107.60662,"lat":-7.577435,"tags":"beach,blue,rancabuaya,sea,sky,water","S2CellId":"14dfc00000000000","result":1337,"accuracy":0.042834163,"title":"Rancabuaya+%236013"}
{"id":4921127638,"url":"http://farm5.staticflickr.com/4101/4921127638_ecbd82d022.jpg","path":"6d7/0cd/6d70cde0522ae3889cde34de0b46f.jpg","date":"2010-07-31","year":2010,"month":7,"lon":107.887405,"lat":-7.079764,"tags":"java,locationinterpolated","S2CellId":"8e39000000000000","result":9446,"accuracy":0.07147432,"title":"P1090074.JPG"}
{"id":2568556258,"url":"http://farm4.staticflickr.com/3122/2568556258_34c5c30b5d.jpg","path":"69e/aae/69eaaede5f299f646fb81429140fc10.jpg","date":"2008-06-04","year":2008,"month":6,"lon":107.55055,"lat":-7.193333,"tags":"cileunca,cloud,lake,landscape,nature,panorama,situ,sky,water","S2CellId":"80e9130000000000","result":7401,"accuracy":0.14688541,"title":"Situ+Cileunca+11"}
{"id":2597597442,"url":"http://farm4.staticflickr.com/3060/2597597442_c5ed7f2324.jpg","path":"bfc/f74/bfcf74c12feb495f1ded19deed50a383.jpg","date":"2008-06-04","year":2008,"month":6,"lon":107.55055,"lat":-7.193333,"tags":"alam,bandung,cileunca,colorful,hijab,inspection,jilbab,kids,lake,panorama,sab,scenery,sekolah,situ,tudung","S2CellId":"2e74000000000000","result":1578,"accuracy":0.03767625,"title":"Inspection+by+Miss+Blue"}
