{"id":2739249931,"url":"http://farm4.staticflickr.com/3231/2739249931_7d4761a15f.jpg","path":"ba4/54f/ba454f4215f559df7f5e9dadf45fcde1.jpg","date":"2008-07-27","year":2008,"month":7,"lon":-64.33594,"lat":-64.92354,"tags":"cambodia,china,humour,laos,signs,translation+error,vietnam","S2CellId":"3442a81000000000","result":2032,"accuracy":0.020056918,"title":"HOLLA"}
{"id":2767611285,"url":"http://farm4.staticflickr.com/3118/2767611285_c94c0d46b5.jpg","path":"5e6/4bb/5e64bb651f78d27e3eb8ca679b372c9b.jpg","date":"2008-07-06","year":2008,"month":7,"lon":-64.33594,"lat":-64.92354,"tags":"angkor+wat,beijing,black+and+white,cambodia,champasak,halong+bay,hanoi,kuala+lumpur,kyle+taylor,laos,malaysia,pakse,petronas,phnom+penh,phu+quoc,portfolio,saigon,si+phon+don,sunset,vientiane,vietnam","S2CellId":"809ad10000000000","result":7121,"accuracy":0.0056468346,"title":"Vientiane+-+182.JPG"}
{"id":2070549452,"url":"http://farm3.staticflickr.com/2093/2070549452_ecc8f73f2c.jpg","path":"f1b/9a5/f1b9a5cbf1ca69428924a128985e5fa.jpg","date":"2005-12-30","year":2005,"month":12,"lon":-64.856415,"lat":-64.822876,"tags":"animal+planet,antarctica,gentoo+penguin,penguin,travel","S2CellId":"bc70000000000000","result":9960,"accuracy":0.1991372,"title":"Gentoo+penguin+with+its+Chick"}
{"id":2767475823,"url":"http://farm4.staticflickr.com/3068/2767475823_9073036cbc.jpg","path":"77a/874/77a87494996c98dde4f2a627c369766e.jpg","date":"2008-05-24","year":2008,"month":5,"lon":-64.33594,"lat":-64.92354,"tags":"angkor+wat,beijing,black+and+white,cambodia,champasak,halong+bay,hanoi,kuala+lumpur,kyle+taylor,laos,malaysia,pakse,petronas,phnom+penh,phu+quoc,portfolio,saigon,si+phon+don,sunset,vientiane,vietnam","S2CellId":"00a6990000000000","result":54,"accuracy":0.030723695,"title":"Abbey+Road+Japanese+Beatles+-+79+copy.JPG"}
