{"id":6046815740,"url":"http://farm7.staticflickr.com/6088/6046815740_7dea506ea5.jpg","path":"25a/698/25a69849ba5d2fb53cc35b3aa6f992f.jpg","date":"2009-02-07","year":2009,"month":2,"lon":31.024017,"lat":-22.690369,"tags":"axiocerses+tjoane","S2CellId":"8814d00000000000","result":8186,"accuracy":0.042186026,"title":"Common+Scarlet+%28Axiocerses+tjoane%29","description":"S59+Mahonie+Loop+near+Punda+Maria%2C+Kruger+NP%2C+SOUTH+AFRICA"}
{"id":11887672376,"url":"http://farm4.staticflickr.com/3796/11887672376_5203b8fcef.jpg","path":"c2c/1d9/c2c1d9b5cac2231248471cc7de4d39c.jpg","date":"2013-12-05","year":2013,"month":12,"lon":31.293955,"lat":-22.431658,"tags":"faidherbia+albida","S2CellId":"1740000000000000","result":1415,"accuracy":0.017947955,"title":"Winter+Thorn+%28Faidherbia+albida%29+pods","description":"S63+Road%2C+Pafuri+area%2C+Kruger+NP%2C+SOUTH+AFRICA"}
{"id":5404429212,"url":"http://farm6.staticflickr.com/5017/5404429212_ba435447e5.jpg","path":"a3f/aee/a3faee040402d162df8c2fa7247efd.jpg","date":"2011-01-01","year":2011,"month":1,"lon":31.307001,"lat":-22.426184,"tags":"corner,crooks,crooks+corner,jomur,kruger+national+park,limpopo+province,pafuri,sanparks,south+africa","S2CellId":"47edc00000000000","result":4703,"accuracy":0.100393645,"title":"Crooks%27+Corner%2C+Pafuri","description":"Arriving+on+our+first+afternoon+at+Crooks%27+Corner+we+were+greeted+by+a+full+river+and+a+rainbow+thrown+in+for+a+little+extra+flavour."}
{"id":11886823095,"url":"http://farm4.staticflickr.com/3764/11886823095_59b0701600.jpg","path":"25d/18d/25d18dae72cd86321296c67a676087.jpg","date":"2013-12-05","year":2013,"month":12,"lon":31.293997,"lat":-22.431736,"tags":"faidherbia+albida","S2CellId":"6b1c000000000000","result":6724,"accuracy":0.020402854,"title":"Winter+Thorn+%28Faidherbia+albida%29+pods","description":"S63+Road%2C+Pafuri+area%2C+Kruger+NP%2C+SOUTH+AFRICA"}
{"id":6929259149,"url":"http://farm8.staticflickr.com/7063/6929259149_3e7f3e304f.jpg","path":"fea/c68/feac688a668ba8bf13204ca6a3897be3.jpg","date":"2012-01-01","year":2012,"month":1,"lon":31.028835,"lat":-22.69499,"tags":"africa,bird,burchell%27s+coucal,centropus+burchellii,knp,kruger,nature,orange,safari,sanparks,south+africa,wildlife","S2CellId":"88d0a631cabb5071","result":8563,"accuracy":0.08157351,"title":"I+was+named+by+William+John+Burchell+you+know.+So+was+the+zebra.","description":"A+solitary+Burchell%27s+coucal+perchs+as+the+sun+rises+above+South+Africa%27s+Kruger+National+Park.++This+species+was+named+by+William+John+Burchell%2C+an+English+19th+century+explorer."}
{"id":6046814444,"url":"http://farm7.staticflickr.com/6200/6046814444_d1c1cc4565.jpg","path":"63c/f3e/63cf3e509244c748390526a3c9be247.jpg","date":"2009-02-07","year":2009,"month":2,"lon":31.024702,"lat":-22.686567,"tags":"adsimilis,dicrurus","S2CellId":"8e47000000000000","result":9481,"accuracy":0.029333891,"title":"Fork-tailed+Drongo+%28Dicrurus+adsimilis%29","description":"S59+Mahonie+Loop+near+Punda+Maria%2C+Kruger+NP%2C+SOUTH+AFRICA"}
{"id":3125548237,"url":"http://farm4.staticflickr.com/3217/3125548237_918b9cf276.jpg","path":"8e6/bdf/8e6bdfed238459394b73b17e2904e28.jpg","date":"2008-11-23","year":2008,"month":11,"lon":31.255932,"lat":-22.428484,"tags":"crocodile,crocodylus,crocodylus+niloticus,kr%C3%BCgernationalpark,kr%C3%BCgerpark,krokodil,kruger,kruger+national+park,kruger+park,nilkrokodil,niloticus,s%C3%BCdafrika,south+africa","S2CellId":"1ed0000000000000","result":1478,"accuracy":0.14263043,"title":"Kruger+23+Nov+08+060","description":"Nile+Crocodile+%28engl.%29%0ANilkrokodil+%28dt.%29%0ACrocodylus+niloticus+%28lat.%29"}
{"id":3126539272,"url":"http://farm4.staticflickr.com/3117/3126539272_6ef36faac8.jpg","path":"da5/55d/da555d6f60b4976b8cadf5197a3b7634.jpg","date":"2008-11-23","year":2008,"month":11,"lon":31.171646,"lat":-22.768267,"tags":"kr%C3%BCgernationalpark,kr%C3%BCgerpark,kruger,kruger+national+park,kruger+park,s%C3%BCdafrika,south+africa","S2CellId":"2cb0000000000000","result":1530,"accuracy":0.33580974,"title":"Kruger+23+Nov+08+139","description":"Wer+beim+Betrachten+der+Fotos+sagt%2C+es+seien+Montagen%2C+der+liegt+falsch+darin%2C+dass+es+kein+Betrug+ist%2C+aber+richtig+darin%2C+dass+ich+die+Fotos+ein+wenig+manipuliert+habe.%0AIn+den+Originalfotos+war+der+Staubteufel+zu+erkennen%2C+aber+sehr+schwach+und+leicht+zu+%C3%BCbersehen.+Daher+habe+ich+die+tats%C3%A4chliche+Staubs%C3%A4ulen+per+Bildbearbeitung+und+automatischer+Rand-%2FFarberkennung+etwas+dunkler+gemacht+und+einen+Hauch+Blau+entfernt%2C+um+sie+deutlicher+vom+Hintergrund+herausstechen+zu+lassen.%0ADas+Resultat+erscheint+aber+der+Realit%C3%A4t+n%C3%A4her+als+das+Originalfoto."}
{"id":9606422564,"url":"http://farm4.staticflickr.com/3834/9606422564_1ed93f5385.jpg","path":"6e1/78a/6e178a14225286f7e044f5bbe0e336df.jpg","date":"2013-08-24","year":2013,"month":8,"lon":31.028137,"lat":-22.657106,"tags":"africa,birds,kruger,kruger+national+park,south+africa,wildlife","S2CellId":"88d0a631cabb5071","result":8563,"accuracy":0.0018881876,"title":"Golden-breasted+Bunting+-+The+Kruger+National+Park"}
