{"id":3920776930,"url":"http://farm4.staticflickr.com/3523/3920776930_a0543a7879.jpg","path":"1cb/8f1/1cb8f118333ba9fe2ca55281fca3f890.jpg","date":"2009-07-15","year":2009,"month":7,"lon":119.2655,"lat":40.28047,"tags":"%E5%9C%9F%E9%97%A8%E5%AD%90,%E6%B2%B3%E5%8C%97,%E7%A7%A6%E7%9A%87%E5%B2%9B,country+side,hebei,qinhuangdao,tumenzi,village","S2CellId":"9663400000000000","result":9895,"accuracy":0.06516805,"title":"Visa+Run+2009+-240"}
{"id":3919976719,"url":"http://farm4.staticflickr.com/3526/3919976719_3b5f16689f.jpg","path":"dd7/511/dd7511ac8a5adc371c5ce21e74253.jpg","date":"2009-07-15","year":2009,"month":7,"lon":119.214,"lat":40.42236,"tags":"%E5%9C%9F%E9%97%A8%E5%AD%90,%E6%B2%B3%E5%8C%97,%E7%A7%A6%E7%9A%87%E5%B2%9B,country+side,hebei,qinhuangdao,tumenzi,village","S2CellId":"314c000000000000","result":1761,"accuracy":0.09877535,"title":"Visa+Run+2009+-200"}
{"id":10344100203,"url":"http://farm8.staticflickr.com/7310/10344100203_4d48331dbf.jpg","path":"704/183/7041838a1aafc69d752f5f9b128d9dbc.jpg","date":"2013-10-04","year":2013,"month":10,"lon":119.75442,"lat":40.009377,"tags":"%E7%A7%A6%E7%9A%87%E5%B2%9B,china,qinhuangdao,shanhaiguan","S2CellId":"35f052f000000000","result":2371,"accuracy":0.23360488,"title":"Shanhaiguan+%E5%B1%B1%E6%B5%B7%E5%85%B3+-+First+Pass+under+Heaven+%E5%A4%A9%E4%B8%8B%E7%AC%AC%E4%B8%80%E5%85%B3","description":"Shanhaiguan+%E5%B1%B1%E6%B5%B7%E5%85%B3+-+First+Pass+under+Heaven+%E5%A4%A9%E4%B8%8B%E7%AC%AC%E4%B8%80%E5%85%B3"}
{"id":3920729198,"url":"http://farm3.staticflickr.com/2654/3920729198_7231bb4332.jpg","path":"3eb/83a/3eb83a577e46c61dcc6fa895f64a5e55.jpg","date":"2009-07-14","year":2009,"month":7,"lon":119.2027,"lat":40.38839,"tags":"%E5%9C%9F%E9%97%A8%E5%AD%90,%E6%B2%B3%E5%8C%97,%E7%A7%A6%E7%9A%87%E5%B2%9B,country+side,hebei,qinhuangdao,tumenzi,village","S2CellId":"9669000000000000","result":9899,"accuracy":0.15410759,"title":"Visa+Run+2009+-033"}
{"id":3647531443,"url":"http://farm4.staticflickr.com/3393/3647531443_08b23ff870.jpg","path":"4ef/44a/4ef44a96a56886ae973b378d94b018.jpg","date":"2008-10-09","year":2008,"month":10,"lon":119.7036,"lat":40.0673,"tags":"china,hebei,shanhaiguan","S2CellId":"357cbc0000000000","result":2320,"accuracy":0.18602876,"title":"DSC01329","description":"%22Mountain+Five+Buddha+Forest+Park%22%2C%3Ca+href%3D%22http%3A%2F%2Fen.wikipedia.org%2Fwiki%2FShanhaiguan%22+target%3D%22_new%22+rel%3D%22nofollow%22%3EShanhaiguan%3C%2Fa%3E%2C+%3Ca+href%3D%22http%3A%2F%2Fen.wikipedia.org%2Fwiki%2FHebei%22+target%3D%22_new%22+rel%3D%22nofollow%22%3EHebei%3C%2Fa%3E%2C+China"}
